{
    "versao": "1.1.0",
    "bibliotecas": [
        "interface",
        "html",
        "html-editor"
    ],
    "id_numerico": "id_forms",
    "tabela": {
        "nome": "forms",
        "nome_especifico": "name",
        "id": "id",
        "id_numerico": "id_forms",
        "status": "status",
        "versao": "version",
        "data_criacao": "created_at",
        "data_modificacao": "updated_at",
        "config": {
            "strategy": "natural_key",
            "natural_key_columns": [
                "language",
                "module",
                "id"
            ],
            "preserve_on_user_modified": [
                "name",
                "fields_schema"
            ],
            "insert_only": false
        },
        "deletar": []
    },
    "resources": {
        "pt-br": {
            "widgets": [
                {
                    "id": "forms",
                    "name": "Formulários",
                    "icon": "clipboard list",
                    "tabela": "forms"
                }
            ],
            "ai_prompts_targets": [
                {
                    "id": "forms",
                    "name": "Formulários"
                }
            ],
            "ai_modes": [
                {
                    "id": "forms",
                    "name": "Formulários",
                    "target": "forms",
                    "default": true,
                    "version": "1.0",
                    "checksum": {
                        "md": ""
                    }
                }
            ],
            "form_info": {
                "name": "Nome do Formulário",
                "id": "id-do-formulario",
                "description": "Descrição do formulário.",
                "fields_schema": {
                    "field_name": "name",
                    "field_email": "email",
                    "form_action": "url-para-onde-enviar-o-formulario",
                    "access_max_simple": 5,
                    "access_max": 10,
                    "force_recaptcha": true,
                    "email": {
                        "recipients": "Nome <email@email.com>; Another Name <another@email.com>",
                        "reply_to": "email@email.com",
                        "reply_to_name": "Nome do Remetente",
                        "subject": "Assunto nº #code#",
                        "message_component": "id-do-componente-de-mensagem"
                    },
                    "redirects": {
                        "success": {
                            "type": "url",
                            "path": "your-page\/success\/"
                        },
                        "error": {
                            "type": "url",
                            "path": "your-page\/error\/"
                        }
                    },
                    "fields": [
                        {
                            "type": "text",
                            "name": "name",
                            "label": "Nome",
                            "required": true
                        },
                        {
                            "type": "email",
                            "name": "email",
                            "label": "E-mail",
                            "required": true
                        },
                        {
                            "type": "textarea",
                            "name": "message",
                            "label": "Mensagem",
                            "required": false
                        }
                    ]
                }
            },
            "layouts": [
                {
                    "name": "Página Simples TailwindCSS",
                    "id": "pagina-simples-tailwindcss",
                    "framework_css": "tailwindcss",
                    "version": "1.4",
                    "checksum": {
                        "html": "5d5efc9849f45c5a257ee4e6fff49d16",
                        "css": "",
                        "combined": "5d5efc9849f45c5a257ee4e6fff49d16"
                    }
                }
            ],
            "components": [
                {
                    "name": "Formulário Definições Informações",
                    "id": "forms-info-definition",
                    "version": "1.1",
                    "checksum": {
                        "html": "a66e09eff43a64bfc85bd492571469b5",
                        "css": "",
                        "combined": "a66e09eff43a64bfc85bd492571469b5"
                    }
                }
            ],
            "templates": [
                {
                    "name": "Formulário de Contato Básico",
                    "id": "forms-contato-basico",
                    "target": "forms",
                    "framework_css": "tailwindcss",
                    "version": "1.2",
                    "checksum": {
                        "html": "8753c36322442ae89b747f38fe605fb6",
                        "css": "",
                        "combined": "8753c36322442ae89b747f38fe605fb6"
                    }
                },
                {
                    "name": "Inscrição na Newsletter",
                    "id": "forms-newsletter-newsletter",
                    "target": "forms",
                    "framework_css": "tailwindcss",
                    "version": "1.2",
                    "checksum": {
                        "html": "4bf6bdafaef9e8f15e16c491a282f65d",
                        "css": "",
                        "combined": "4bf6bdafaef9e8f15e16c491a282f65d"
                    }
                },
                {
                    "name": "Registro de Usuário",
                    "id": "forms-registro-usuario",
                    "target": "forms",
                    "framework_css": "tailwindcss",
                    "version": "1.2",
                    "checksum": {
                        "html": "b8f6a4b275bd7d992b87541060e9e9d4",
                        "css": "",
                        "combined": "b8f6a4b275bd7d992b87541060e9e9d4"
                    }
                },
                {
                    "name": "Pesquisa de Satisfação",
                    "id": "forms-pesquisa-satisfacao",
                    "target": "forms",
                    "framework_css": "tailwindcss",
                    "version": "1.2",
                    "checksum": {
                        "html": "ec713cf91f1e9f8ee6326d59a41997ef",
                        "css": "",
                        "combined": "ec713cf91f1e9f8ee6326d59a41997ef"
                    }
                },
                {
                    "name": "Suporte Técnico",
                    "id": "forms-suporte-tecnico",
                    "target": "forms",
                    "framework_css": "tailwindcss",
                    "version": "1.2",
                    "checksum": {
                        "html": "7369fec0015bad20f27abb1501d2f33c",
                        "css": "",
                        "combined": "7369fec0015bad20f27abb1501d2f33c"
                    }
                }
            ],
            "pages": [
                {
                    "name": "Formulários Listar",
                    "id": "forms-list",
                    "layout": "layout-administrativo-do-gestor",
                    "path": "forms\/",
                    "type": "system",
                    "option": "listar",
                    "root": true,
                    "version": "1.0",
                    "checksum": {
                        "html": "",
                        "css": "",
                        "combined": ""
                    }
                },
                {
                    "name": "Formulários Visualizar",
                    "id": "forms-view",
                    "layout": "layout-administrativo-do-gestor",
                    "path": "forms\/view\/",
                    "type": "system",
                    "option": "visualizar",
                    "version": "1.10",
                    "checksum": {
                        "html": "3dbdc176cdc7b3b133495589fcb996bd",
                        "css": "",
                        "combined": "3dbdc176cdc7b3b133495589fcb996bd"
                    }
                },
                {
                    "name": "Formulários Adicionar",
                    "id": "forms-adicionar",
                    "layout": "layout-administrativo-do-gestor",
                    "path": "forms\/adicionar\/",
                    "type": "system",
                    "option": "adicionar",
                    "version": "1.11",
                    "checksum": {
                        "html": "f6b07cf23c4a69686d989c59a1e1f385",
                        "css": "aa43d6aa4dec695c666f726474800b97",
                        "combined": "7146190c4fe26b966efa017d7f7edd76"
                    }
                },
                {
                    "name": "Formulários Editar",
                    "id": "forms-editar",
                    "layout": "layout-administrativo-do-gestor",
                    "path": "forms\/editar\/",
                    "type": "system",
                    "option": "editar",
                    "version": "1.9",
                    "checksum": {
                        "html": "9ec559b392ab542f7e3824472ca51c63",
                        "css": "aa43d6aa4dec695c666f726474800b97",
                        "combined": "a9b71be991556a9ab0a1cd0e69cc42cf"
                    }
                },
                {
                    "name": "Formulários Clonar",
                    "id": "forms-clonar",
                    "layout": "layout-administrativo-do-gestor",
                    "path": "forms\/clonar\/",
                    "type": "system",
                    "option": "clonar",
                    "version": "1.8",
                    "checksum": {
                        "html": "185a9237aa5f73cf0f2442190b8cc006",
                        "css": "aa43d6aa4dec695c666f726474800b97",
                        "combined": "8d6026e11af3496728c62e6e924b234e"
                    }
                },
                {
                    "name": "Forms Test Email Page",
                    "id": "forms-test-email-page",
                    "layout": "pagina-simples-tailwindcss",
                    "path": "forms\/test-email-page\/",
                    "type": "system",
                    "option": "test-email-page",
                    "framework_css": "tailwindcss",
                    "version": "1.1",
                    "checksum": {
                        "html": "752b731f15b5cb2b87db994b3599a35f",
                        "css": "",
                        "combined": "752b731f15b5cb2b87db994b3599a35f"
                    }
                }
            ],
            "variables": [
                {
                    "id": "form-name-label",
                    "value": "Nome",
                    "type": "string"
                },
                {
                    "id": "form-module-placeholder",
                    "value": "Selecione opcionalmente um módulo",
                    "type": "string"
                },
                {
                    "id": "form-module-label",
                    "value": "Módulo",
                    "type": "string"
                },
                {
                    "id": "form-template_id-label",
                    "value": "Template (Recurso)",
                    "type": "string"
                },
                {
                    "id": "form-fields_schema-label",
                    "value": "Esquema dos Campos",
                    "type": "string"
                },
                {
                    "id": "form-description-label",
                    "value": "Descrição",
                    "type": "string"
                }
            ]
        },
        "en": {
            "widgets": [
                {
                    "id": "forms",
                    "name": "Forms",
                    "icon": "clipboard list",
                    "tabela": "forms"
                }
            ],
            "ai_prompts_targets": [
                {
                    "id": "forms",
                    "name": "Forms"
                }
            ],
            "ai_modes": [
                {
                    "id": "forms",
                    "name": "Forms",
                    "target": "forms",
                    "default": true,
                    "version": "1.0",
                    "checksum": {
                        "md": ""
                    }
                }
            ],
            "form_info": {
                "name": "Form Name",
                "id": "form-id",
                "description": "Form description.",
                "fields_schema": {
                    "field_name": "name",
                    "field_email": "email",
                    "form_action": "url-for-where-to-send-form",
                    "access_max_simple": 5,
                    "access_max": 10,
                    "force_recaptcha": true,
                    "email": {
                        "recipients": "Name <email@email.com>; Another Name <another@email.com>",
                        "reply_to": "email@email.com",
                        "reply_to_name": "Sender Name",
                        "subject": "Subject nº #code#",
                        "template": "template-component-id"
                    },
                    "redirects": {
                        "success": {
                            "type": "url",
                            "path": "your-page\/success\/"
                        },
                        "error": {
                            "type": "url",
                            "path": "your-page\/error\/"
                        }
                    },
                    "fields": [
                        {
                            "type": "text",
                            "name": "name",
                            "label": "Name",
                            "required": true
                        },
                        {
                            "type": "email",
                            "name": "email",
                            "label": "E-mail",
                            "required": true
                        },
                        {
                            "type": "textarea",
                            "name": "message",
                            "label": "Message",
                            "required": false
                        }
                    ]
                }
            },
            "layouts": [
                {
                    "name": "Simple Page TailwindCSS",
                    "id": "pagina-simples-tailwindcss",
                    "framework_css": "tailwindcss",
                    "version": "1.4",
                    "checksum": {
                        "html": "",
                        "css": "",
                        "combined": ""
                    }
                }
            ],
            "components": [
                {
                    "name": "Forms Info Definition",
                    "id": "forms-info-definition",
                    "version": "1.1",
                    "checksum": {
                        "html": "2db5cb9601ce1961567b1aa20cfaed94",
                        "css": "",
                        "combined": "2db5cb9601ce1961567b1aa20cfaed94"
                    }
                }
            ],
            "templates": [
                {
                    "name": "Basic Contact Form",
                    "id": "forms-contato-basico",
                    "target": "forms",
                    "framework_css": "tailwindcss",
                    "version": "1.2",
                    "checksum": {
                        "html": "07a6c123f9a7d70029f71c504651d59e",
                        "css": "",
                        "combined": "07a6c123f9a7d70029f71c504651d59e"
                    }
                },
                {
                    "name": "Newsletter Subscription",
                    "id": "forms-newsletter-newsletter",
                    "target": "forms",
                    "framework_css": "tailwindcss",
                    "version": "1.2",
                    "checksum": {
                        "html": "64c9e2af0bf687f8690b0175508e237b",
                        "css": "",
                        "combined": "64c9e2af0bf687f8690b0175508e237b"
                    }
                },
                {
                    "name": "User Registration",
                    "id": "forms-registro-usuario",
                    "target": "forms",
                    "framework_css": "tailwindcss",
                    "version": "1.2",
                    "checksum": {
                        "html": "5acd05ef9330c9bb456b5518bb430939",
                        "css": "",
                        "combined": "5acd05ef9330c9bb456b5518bb430939"
                    }
                },
                {
                    "name": "Satisfaction Survey",
                    "id": "forms-pesquisa-satisfacao",
                    "target": "forms",
                    "framework_css": "tailwindcss",
                    "version": "1.2",
                    "checksum": {
                        "html": "fc0894afbab9cf3672a0e679f04f7069",
                        "css": "",
                        "combined": "fc0894afbab9cf3672a0e679f04f7069"
                    }
                },
                {
                    "name": "Technical Support",
                    "id": "forms-suporte-tecnico",
                    "target": "forms",
                    "framework_css": "tailwindcss",
                    "version": "1.2",
                    "checksum": {
                        "html": "f1e9e7d4c43fcf902a1e2f2d0cb268cd",
                        "css": "",
                        "combined": "f1e9e7d4c43fcf902a1e2f2d0cb268cd"
                    }
                }
            ],
            "pages": [
                {
                    "name": "Forms List",
                    "id": "forms-list",
                    "layout": "layout-administrativo-do-gestor",
                    "path": "forms\/",
                    "type": "system",
                    "option": "listar",
                    "root": true,
                    "version": "1.0",
                    "checksum": {
                        "html": "",
                        "css": "",
                        "combined": ""
                    }
                },
                {
                    "name": "Forms View",
                    "id": "forms-view",
                    "layout": "layout-administrativo-do-gestor",
                    "path": "forms\/view\/",
                    "type": "system",
                    "option": "visualizar",
                    "version": "1.13",
                    "checksum": {
                        "html": "a62362020eafb15e85002e9a752419a1",
                        "css": "",
                        "combined": "a62362020eafb15e85002e9a752419a1"
                    }
                },
                {
                    "name": "Forms Add",
                    "id": "forms-adicionar",
                    "layout": "layout-administrativo-do-gestor",
                    "path": "forms\/adicionar\/",
                    "type": "system",
                    "option": "adicionar",
                    "version": "1.13",
                    "checksum": {
                        "html": "fd0a564bf934fa4beb9b9e419835e8fb",
                        "css": "aa43d6aa4dec695c666f726474800b97",
                        "combined": "2a6e5edada0d8dc8d94dd01ecf88661f"
                    }
                },
                {
                    "name": "Forms Edit",
                    "id": "forms-editar",
                    "layout": "layout-administrativo-do-gestor",
                    "path": "forms\/editar\/",
                    "type": "system",
                    "option": "editar",
                    "version": "1.11",
                    "checksum": {
                        "html": "96793c1d186a8936e67f2c6ee51ce85b",
                        "css": "aa43d6aa4dec695c666f726474800b97",
                        "combined": "e742955bbcd3c06f9ce6501e679b8c33"
                    }
                },
                {
                    "name": "Forms Clone",
                    "id": "forms-clonar",
                    "layout": "layout-administrativo-do-gestor",
                    "path": "forms\/clonar\/",
                    "type": "system",
                    "option": "clonar",
                    "version": "1.10",
                    "checksum": {
                        "html": "4f23fc8e7ac221a660d42b301c98faff",
                        "css": "aa43d6aa4dec695c666f726474800b97",
                        "combined": "acc1e2deaf6240721e5d65a27fb692bf"
                    }
                },
                {
                    "name": "Forms Test Email Page",
                    "id": "forms-test-email-page",
                    "layout": "pagina-simples-tailwindcss",
                    "path": "forms\/test-email-page\/",
                    "type": "system",
                    "option": "test-email-page",
                    "framework_css": "tailwindcss",
                    "version": "1.1",
                    "checksum": {
                        "html": "752b731f15b5cb2b87db994b3599a35f",
                        "css": "",
                        "combined": "752b731f15b5cb2b87db994b3599a35f"
                    }
                }
            ],
            "variables": [
                {
                    "id": "form-name-label",
                    "value": "Name",
                    "type": "string"
                },
                {
                    "id": "form-module-placeholder",
                    "value": "Optionally select a module",
                    "type": "string"
                },
                {
                    "id": "form-module-label",
                    "value": "Module",
                    "type": "string"
                },
                {
                    "id": "form-template_id-label",
                    "value": "Template (Resource)",
                    "type": "string"
                },
                {
                    "id": "form-fields_schema-label",
                    "value": "Fields Schema",
                    "type": "string"
                },
                {
                    "id": "form-description-label",
                    "value": "Description",
                    "type": "string"
                }
            ]
        }
    }
}