[
    {
        "id_paginas": 178,
        "id_usuarios": 1,
        "layout_id": "layout-administrativo-do-gestor",
        "nome": "Agendamentos",
        "id": "agendamentos",
        "language": "pt-br",
        "caminho": "agendamentos\/",
        "tipo": "sistema",
        "modulo": "agendamentos",
        "opcao": "administrar",
        "raiz": 1,
        "sem_permissao": null,
        "html": "<div class=\"ui attached icon message\">\n    <i class=\"calendar alternate icon\"><\/i>\n    <div class=\"content\">\n        <div class=\"header\">\n            Instruções\n        <\/div>\n        <p>Selecione uma data das disponíveis para visualizar a lista dos atendimentos e modifique as opções abaixo conforme convir.<\/p>\n    <\/div>\n<\/div>\n<form class=\"ui form attached fluid segment\" method=\"post\" id=\"formAgendamentos\">\n    <div class=\"two fields\">\n        <div class=\"field\">\n            <label>Data dos Agendamentos<\/label>\n            <input type=\"hidden\" name=\"data\" class=\"agendamentoData\">\n            <div class=\"ui calendar\"><\/div>\n        <\/div>\n        <div class=\"field\">\n            <label>Estado dos Agendamentos<\/label>\n            <select class=\"ui dropdown\" name=\"estado\">\n                <option value=\"\">Selecione um estado...<\/option>\n                <option value=\"pre\">Pré-Agendamentos<\/option>\n                <option value=\"aguardando\">Aguardando Confirmação<\/option>\n                <option value=\"confirmados\">Confirmados<\/option>\n                <option value=\"finalizados\">Finalizados<\/option>\n            <\/select>\n        <\/div>\n    <\/div>\n    <div class=\"escondido resultados\">\n        <div class=\"ui basic fitted segment\">\n            <span class=\"dataSelecionada\">\n                <div class=\"ui primary large label\">\n                    <i class=\"calendar check icon\"><\/i>\n                    <span class=\"dataSelecionadaValor\"><\/span>\n                <\/div>\n            <\/span>\n            &nbsp;\n            <span class=\"totalPessoas escondido\">\n                <div class=\"ui green large label\">\n                    <i class=\"users icon\"><\/i>\n                    Total: \n                    <span class=\"totalValor\">0<\/span>\n                <\/div>\n            <\/span>\n            &nbsp;\n            <a class=\"ui orange large label imprimirBtn escondido\">\n                <i class=\"print icon\"><\/i>\n                Imprimir\n            <\/a>\n        <\/div>\n        <div class=\"tabelaPessoas escondido\">\n            <!-- tabela-pessoas < --><table class=\"ui unstackable celled very compact table\">\n                <thead>\n                    <tr>\n                        <th>Nome<\/th>\n                        <!-- th-senha < --><th>Senha<\/th><!-- th-senha > -->\n                        <th>Acompanhantes<\/th>\n                        <!-- th-email < --><th>Email<\/th><!-- th-email > -->\n                    <\/tr>\n                <\/thead>\n                <tbody>\n                    <!-- cel-agendamento < --><tr>\n                    <td>@[[nome]]@<\/td>\n                    <!-- td-senha < --><td>@[[senha]]@<\/td><!-- td-senha > -->\n                    <td>\n                        <!-- td-acompanhantes < --><table class=\"ui definition very compact table\">\n                            <tbody>\n                                <!-- cel-acompanhante < --><tr>\n                                    <td class=\"nowrap\" style=\"width: 80px;\">Acompanhante @[[num]]@<\/td>\n                                    <td>@[[acompanhante]]@<\/td>\n                                <\/tr><!-- cel-acompanhante > -->\n                            <\/tbody>\n                        <\/table><!-- td-acompanhantes > -->\n                    <\/td>\n                    <!-- td-email < --><td>\n                    \t<!-- enviado < --><div class=\"ui green large label\">\n                            <i class=\"paper plane icon\"><\/i>\n                            Enviado\n                        <\/div><!-- enviado > -->\n                    \t<!-- nao-enviado < --><div class=\"ui yellow large label nowrap\">\n                            <i class=\"exclamation triangle icon\"><\/i>\n                            Não Enviado\n                        <\/div><!-- nao-enviado > -->\n                    <\/td><!-- td-email > -->\n                    <\/tr><!-- cel-agendamento > -->\n                <\/tbody>\n            <\/table><!-- tabela-pessoas > -->\n        <\/div>\n    <\/div>\n<\/form>",
        "css": ".escondido{\n    display:none;\n}\n.nowrap{\n    white-space: nowrap;\n}",
        "status": "A",
        "versao": 1,
        "data_criacao": "2025-08-25 18:23:12",
        "data_modificacao": "2025-08-25 18:23:12",
        "user_modified": 0,
        "system_updated": 0,
        "html_updated": null,
        "css_updated": null,
        "framework_css": null,
        "file_version": "1.1",
        "checksum": "{\"html\":\"0b9c59644a65900610cf7402b6ad6a56\",\"css\":\"1552f7d68f8c4beacd681d8ed82cd7b5\",\"combined\":\"aba0b96eda9087a057496ea295c48d98\"}"
    },
    {
        "id_paginas": 179,
        "id_usuarios": 1,
        "layout_id": "layout-administrativo-do-gestor",
        "nome": "Cupons de Prioridade",
        "id": "cupons-de-prioridade",
        "language": "pt-br",
        "caminho": "agendamentos\/cupons-de-prioridade\/",
        "tipo": "sistema",
        "modulo": "agendamentos",
        "opcao": "listar",
        "raiz": null,
        "sem_permissao": null,
        "html": "",
        "css": null,
        "status": "A",
        "versao": 1,
        "data_criacao": "2025-08-25 18:23:12",
        "data_modificacao": "2025-08-25 18:23:12",
        "user_modified": 0,
        "system_updated": 0,
        "html_updated": null,
        "css_updated": null,
        "framework_css": null,
        "file_version": "1.0",
        "checksum": "{\"html\":\"\",\"css\":\"\",\"combined\":\"\"}"
    },
    {
        "id_paginas": 180,
        "id_usuarios": 1,
        "layout_id": "layout-administrativo-do-gestor",
        "nome": "Cupons de Prioridade - Adicionar",
        "id": "cupons-de-prioridade-adicionar",
        "language": "pt-br",
        "caminho": "agendamentos\/cupons-de-prioridade\/adicionar\/",
        "tipo": "sistema",
        "modulo": "agendamentos",
        "opcao": "adicionar",
        "raiz": null,
        "sem_permissao": null,
        "html": "<div class=\"field\">\n    <label>#form-name-label#<\/label>\n    <input type=\"text\" name=\"nome\" placeholder=\"#form-name-placeholder#\">\n<\/div>\n<div class=\"three fields\">\n    <div class=\"field\">\n        <label>#form-quantity-label#<\/label>\n        <input type=\"text\" name=\"quantidade\" placeholder=\"#form-quantity-placeholder#\" class=\"quantidade\">\n    <\/div>\n    <div class=\"field\">\n        <label>#form-valid-from-label#<\/label>\n        <div class=\"ui calendar\" id=\"rangestart\">\n            <div class=\"ui input left icon\">\n                <i class=\"calendar icon\"><\/i>\n                <input type=\"text\" name=\"valido_de\" placeholder=\"#form-valid-from-placeholder#\">\n            <\/div>\n        <\/div>\n    <\/div>\n    <div class=\"field\">\n        <label>#form-valid-until-label#<\/label>\n        <div class=\"ui calendar\" id=\"rangeend\">\n            <div class=\"ui input left icon\">\n                <i class=\"calendar icon\"><\/i>\n                <input type=\"text\" name=\"valido_ate\" placeholder=\"#form-valid-until-placeholder#\">\n            <\/div>\n        <\/div>\n    <\/div>\n<\/div>",
        "css": null,
        "status": "A",
        "versao": 1,
        "data_criacao": "2025-08-25 18:23:12",
        "data_modificacao": "2025-08-25 18:23:12",
        "user_modified": 0,
        "system_updated": 0,
        "html_updated": null,
        "css_updated": null,
        "framework_css": null,
        "file_version": "1.1",
        "checksum": "{\"html\":\"eb6e48c6a12f6cbd6b3bfaf59b492cc3\",\"css\":\"\",\"combined\":\"eb6e48c6a12f6cbd6b3bfaf59b492cc3\"}"
    },
    {
        "id_paginas": 181,
        "id_usuarios": 1,
        "layout_id": "layout-administrativo-do-gestor",
        "nome": "Cupons de Prioridade - Editar",
        "id": "cupons-de-prioridade-editar",
        "language": "pt-br",
        "caminho": "agendamentos\/cupons-de-prioridade\/editar\/",
        "tipo": "sistema",
        "modulo": "agendamentos",
        "opcao": "editar",
        "raiz": null,
        "sem_permissao": null,
        "html": "<div class=\"field\">\n    <label>#form-name-label#<\/label>\n    <input type=\"text\" name=\"nome\" placeholder=\"#form-name-placeholder#\" value=\"#nome#\">\n<\/div>\n<div class=\"three fields\">\n    <div class=\"field\">\n        <label>#form-quantity-label#<\/label>\n        <input type=\"text\" name=\"quantidade\" placeholder=\"#form-quantity-placeholder#\" class=\"quantidade\" value=\"#quantidade#\">\n    <\/div>\n    <div class=\"field\">\n        <label>#form-valid-from-label#<\/label>\n        <div class=\"ui calendar\" id=\"rangestart\">\n            <div class=\"ui input left icon\">\n                <i class=\"calendar icon\"><\/i>\n                <input type=\"text\" name=\"valido_de\" placeholder=\"#form-valid-from-placeholder#\" value=\"#valido_de#\">\n            <\/div>\n        <\/div>\n    <\/div>\n    <div class=\"field\">\n        <label>#form-valid-until-label#<\/label>\n        <div class=\"ui calendar\" id=\"rangeend\">\n            <div class=\"ui input left icon\">\n                <i class=\"calendar icon\"><\/i>\n                <input type=\"text\" name=\"valido_ate\" placeholder=\"#form-valid-until-placeholder#\" value=\"#valido_ate#\">\n            <\/div>\n        <\/div>\n    <\/div>\n<\/div>",
        "css": null,
        "status": "A",
        "versao": 1,
        "data_criacao": "2025-08-25 18:23:12",
        "data_modificacao": "2025-08-25 18:23:12",
        "user_modified": 0,
        "system_updated": 0,
        "html_updated": null,
        "css_updated": null,
        "framework_css": null,
        "file_version": "1.1",
        "checksum": "{\"html\":\"b95c89e71394abe8088ca71a1db84a56\",\"css\":\"\",\"combined\":\"b95c89e71394abe8088ca71a1db84a56\"}"
    },
    {
        "id_paginas": 182,
        "id_usuarios": 1,
        "layout_id": "layout-administrativo-do-gestor",
        "nome": "Configurações de Agendamentos",
        "id": "configuracoes-de-agendamentos",
        "language": "pt-br",
        "caminho": "configuracoes-agendamentos\/",
        "tipo": "sistema",
        "modulo": "configuracoes-agendamentos",
        "opcao": "config",
        "raiz": 1,
        "sem_permissao": null,
        "html": "<!-- configuracao-hosts -->",
        "css": null,
        "status": "A",
        "versao": 1,
        "data_criacao": "2025-08-25 18:23:12",
        "data_modificacao": "2025-08-25 18:23:12",
        "user_modified": 0,
        "system_updated": 0,
        "html_updated": null,
        "css_updated": null,
        "framework_css": null,
        "file_version": "1.1",
        "checksum": "{\"html\":\"e76a85864ca2b11590fa6c0df6cae939\",\"css\":\"\",\"combined\":\"e76a85864ca2b11590fa6c0df6cae939\"}"
    },
    {
        "id_paginas": 183,
        "id_usuarios": 1,
        "layout_id": "layout-administrativo-do-gestor",
        "nome": "Configurações de Escala",
        "id": "configuracoes-de-escala",
        "language": "pt-br",
        "caminho": "configuracoes-escalas\/",
        "tipo": "sistema",
        "modulo": "configuracoes-escalas",
        "opcao": "config",
        "raiz": 1,
        "sem_permissao": null,
        "html": null,
        "css": null,
        "status": "A",
        "versao": 1,
        "data_criacao": "2025-08-25 18:23:12",
        "data_modificacao": "2025-08-25 18:23:12",
        "user_modified": 0,
        "system_updated": 0,
        "html_updated": null,
        "css_updated": null,
        "framework_css": null,
        "file_version": "1.0",
        "checksum": "{\"html\":\"\",\"css\":\"\",\"combined\":\"\"}"
    },
    {
        "id_paginas": 184,
        "id_usuarios": 1,
        "layout_id": "layout-administrativo-do-gestor",
        "nome": "Escalas",
        "id": "escalas",
        "language": "pt-br",
        "caminho": "escalas\/",
        "tipo": "sistema",
        "modulo": "escalas",
        "opcao": "administrar",
        "raiz": 1,
        "sem_permissao": null,
        "html": "<div class=\"ui attached icon message\">\n    <i class=\"calendar check icon\"><\/i>\n    <div class=\"content\">\n        <div class=\"header\">\n            Instruções\n        <\/div>\n        <p>Selecione uma data das disponíveis para visualizar a lista das escalas e modifique as opções abaixo conforme convir.<\/p>\n    <\/div>\n<\/div>\n<form class=\"ui form attached fluid segment\" method=\"post\" id=\"formEscalas\">\n    <div class=\"two fields\">\n        <div class=\"field\">\n            <label>Data das Escalas<\/label>\n            <input type=\"hidden\" name=\"data\" class=\"escalaData\">\n            <div class=\"ui calendar\"><\/div>\n        <\/div>\n        <div class=\"field\">\n            <label>Estado das Escalas<\/label>\n            <select class=\"ui dropdown\" name=\"estado\">\n                <option value=\"\">Selecione um estado...<\/option>\n                <option value=\"novo\">Inscrição<\/option>\n                <option value=\"aguardando\">Aguardando Confirmação<\/option>\n                <option value=\"confirmados\">Confirmados \/ Vagas Residuais<\/option>\n                <option value=\"nao-confirmados\">Não Confirmados<\/option>\n                <option value=\"cancelados\">Cancelados<\/option>\n            <\/select>\n        <\/div>\n    <\/div>\n    <div class=\"escondido resultados\">\n        <div class=\"ui basic fitted segment\">\n            <span class=\"dataSelecionada\">\n                <div class=\"ui primary large label\">\n                    <i class=\"calendar check icon\"><\/i>\n                    <span class=\"dataSelecionadaValor\"><\/span>\n                <\/div>\n            <\/span>\n            &nbsp;\n            <span class=\"totalPessoas escondido\">\n                <div class=\"ui green large label\">\n                    <i class=\"users icon\"><\/i>\n                    Total: \n                    <span class=\"totalValor\">0<\/span>\n                <\/div>\n            <\/span>\n            &nbsp;\n            <a class=\"ui orange large label imprimirBtn escondido\">\n                <i class=\"print icon\"><\/i>\n                Imprimir\n            <\/a>\n        <\/div>\n        <div class=\"tabelaPessoas escondido\">\n            <!-- tabela-pessoas < --><table class=\"ui unstackable celled very compact table\">\n                <thead>\n                    <tr>\n                        <th>Nome<\/th>\n                        <!-- th-email < --><th>Email<\/th><!-- th-email > -->\n                    <\/tr>\n                <\/thead>\n                <tbody>\n                    <!-- cel-escala < --><tr>\n                    <td>@[[nome]]@<\/td>\n                    <!-- td-email < --><td>\n                    \t<!-- enviado < --><div class=\"ui green large label\">\n                            <i class=\"paper plane icon\"><\/i>\n                            Enviado\n                        <\/div><!-- enviado > -->\n                    \t<!-- nao-enviado < --><div class=\"ui yellow large label nowrap\">\n                            <i class=\"exclamation triangle icon\"><\/i>\n                            Não Enviado\n                        <\/div><!-- nao-enviado > -->\n                    <\/td><!-- td-email > -->\n                    <\/tr><!-- cel-escala > -->\n                <\/tbody>\n            <\/table><!-- tabela-pessoas > -->\n        <\/div>\n    <\/div>\n<\/form>",
        "css": ".escondido{\n    display:none;\n}\n.nowrap{\n    white-space: nowrap;\n}",
        "status": "A",
        "versao": 1,
        "data_criacao": "2025-08-25 18:23:12",
        "data_modificacao": "2025-08-25 18:23:12",
        "user_modified": 0,
        "system_updated": 0,
        "html_updated": null,
        "css_updated": null,
        "framework_css": null,
        "file_version": "1.1",
        "checksum": "{\"html\":\"34ba64912e38b58d600f95d0579c2568\",\"css\":\"1552f7d68f8c4beacd681d8ed82cd7b5\",\"combined\":\"8f0f0cbcad391b83bebcb4c3cdbf346d\"}"
    },
    {
        "id_paginas": 187,
        "id_usuarios": 1,
        "layout_id": "layout-administrativo-do-gestor",
        "nome": "Admin Atualizações - Disparar",
        "id": "admin-atualizacoes-disparar",
        "language": "pt-br",
        "caminho": "admin-atualizacoes\/disparar\/",
        "tipo": "sistema",
        "modulo": "admin-atualizacoes",
        "opcao": "disparar",
        "raiz": null,
        "sem_permissao": null,
        "html": "<h1 class=\"ui header\">@[[updates-title]]@ - Disparar<\/h1>\r\n<div>#dynamic-content#<\/div>",
        "css": null,
        "status": "A",
        "versao": 1,
        "data_criacao": "2025-08-26 17:56:38",
        "data_modificacao": "2025-08-26 17:56:38",
        "user_modified": 0,
        "system_updated": 0,
        "html_updated": null,
        "css_updated": null,
        "framework_css": null,
        "file_version": "1.1",
        "checksum": "{\"html\":\"a67e7aa3cfe5a177bbadd7a1d4d4c750\",\"css\":\"\",\"combined\":\"a67e7aa3cfe5a177bbadd7a1d4d4c750\"}"
    }
]