[
    {
        "id_variaveis": 1198,
        "linguagem_codigo": "pt-br",
        "modulo": "agendamentos",
        "id": "label-button-admin",
        "valor": "Administração",
        "tipo": "string",
        "grupo": null,
        "descricao": "Label do botão administrar",
        "user_modified": 0,
        "system_updated": 0,
        "value_updated": null
    },
    {
        "id_variaveis": 1199,
        "linguagem_codigo": "pt-br",
        "modulo": "agendamentos",
        "id": "tooltip-button-admin",
        "valor": "Clique para administrar os agendamentos",
        "tipo": "string",
        "grupo": null,
        "descricao": "Tooltip do botão administrar",
        "user_modified": 0,
        "system_updated": 0,
        "value_updated": null
    },
    {
        "id_variaveis": 1200,
        "linguagem_codigo": "pt-br",
        "modulo": "agendamentos",
        "id": "label-button-coupon",
        "valor": "Cupons de Prioridade",
        "tipo": "string",
        "grupo": null,
        "descricao": "Label do botão cupom de prioridade",
        "user_modified": 0,
        "system_updated": 0,
        "value_updated": null
    },
    {
        "id_variaveis": 1201,
        "linguagem_codigo": "pt-br",
        "modulo": "agendamentos",
        "id": "tooltip-button-coupon",
        "valor": "Clique para gerenciar os cupons de prioridade",
        "tipo": "string",
        "grupo": null,
        "descricao": "Tooltip do botão cupom de prioridade",
        "user_modified": 0,
        "system_updated": 0,
        "value_updated": null
    },
    {
        "id_variaveis": 1202,
        "linguagem_codigo": "pt-br",
        "modulo": "agendamentos",
        "id": "form-name-label",
        "valor": "Nome",
        "tipo": "string",
        "grupo": null,
        "descricao": null,
        "user_modified": 0,
        "system_updated": 0,
        "value_updated": null
    },
    {
        "id_variaveis": 1203,
        "linguagem_codigo": "pt-br",
        "modulo": "agendamentos",
        "id": "form-name-placeholder",
        "valor": "Nome",
        "tipo": "string",
        "grupo": null,
        "descricao": null,
        "user_modified": 0,
        "system_updated": 0,
        "value_updated": null
    },
    {
        "id_variaveis": 1204,
        "linguagem_codigo": "pt-br",
        "modulo": "agendamentos",
        "id": "form-quantity-label",
        "valor": "Quantidade",
        "tipo": "string",
        "grupo": null,
        "descricao": null,
        "user_modified": 0,
        "system_updated": 0,
        "value_updated": null
    },
    {
        "id_variaveis": 1205,
        "linguagem_codigo": "pt-br",
        "modulo": "agendamentos",
        "id": "form-quantity-placeholder",
        "valor": "Quantidade",
        "tipo": "string",
        "grupo": null,
        "descricao": null,
        "user_modified": 0,
        "system_updated": 0,
        "value_updated": null
    },
    {
        "id_variaveis": 1206,
        "linguagem_codigo": "pt-br",
        "modulo": "agendamentos",
        "id": "form-valid-from-label",
        "valor": "Válido De",
        "tipo": "string",
        "grupo": null,
        "descricao": null,
        "user_modified": 0,
        "system_updated": 0,
        "value_updated": null
    },
    {
        "id_variaveis": 1207,
        "linguagem_codigo": "pt-br",
        "modulo": "agendamentos",
        "id": "form-valid-from-placeholder",
        "valor": "Escolha uma data...",
        "tipo": "string",
        "grupo": null,
        "descricao": null,
        "user_modified": 0,
        "system_updated": 0,
        "value_updated": null
    },
    {
        "id_variaveis": 1208,
        "linguagem_codigo": "pt-br",
        "modulo": "agendamentos",
        "id": "form-valid-until-label",
        "valor": "Válido Até",
        "tipo": "string",
        "grupo": null,
        "descricao": null,
        "user_modified": 0,
        "system_updated": 0,
        "value_updated": null
    },
    {
        "id_variaveis": 1209,
        "linguagem_codigo": "pt-br",
        "modulo": "agendamentos",
        "id": "form-valid-until-placeholder",
        "valor": "Escolha uma data...",
        "tipo": "string",
        "grupo": null,
        "descricao": null,
        "user_modified": 0,
        "system_updated": 0,
        "value_updated": null
    },
    {
        "id_variaveis": 1210,
        "linguagem_codigo": "pt-br",
        "modulo": "agendamentos",
        "id": "label-print",
        "valor": "Imprimir Cupons",
        "tipo": "string",
        "grupo": null,
        "descricao": null,
        "user_modified": 0,
        "system_updated": 0,
        "value_updated": null
    },
    {
        "id_variaveis": 1211,
        "linguagem_codigo": "pt-br",
        "modulo": "agendamentos",
        "id": "tooltip-print",
        "valor": "Clique para imprimir os Cupons de Prioridade",
        "tipo": "string",
        "grupo": null,
        "descricao": null,
        "user_modified": 0,
        "system_updated": 0,
        "value_updated": null
    },
    {
        "id_variaveis": 1212,
        "linguagem_codigo": "pt-br",
        "modulo": "agendamentos",
        "id": "alert-cupons-not-found",
        "valor": "Cupom de prioridade não encontrado. Favor tente novamente.",
        "tipo": "string",
        "grupo": null,
        "descricao": null,
        "user_modified": 0,
        "system_updated": 0,
        "value_updated": null
    },
    {
        "id_variaveis": 1213,
        "linguagem_codigo": "pt-br",
        "modulo": "agendamentos",
        "id": "alert-cupons-expired",
        "valor": "Estes cupons estão vencidos, favor alterar o campo <b>Válido Até<\/b> por uma data maior que a do dia de hoje e tente novamente.",
        "tipo": "string",
        "grupo": null,
        "descricao": null,
        "user_modified": 0,
        "system_updated": 0,
        "value_updated": null
    },
    {
        "id_variaveis": 1214,
        "linguagem_codigo": "pt-br",
        "modulo": "configuracoes-agendamentos",
        "id": "agendamento-ativacao",
        "valor": "1",
        "tipo": "bool",
        "grupo": "host-both",
        "descricao": "Ativar\/Desativar o sistema de agendamento.",
        "user_modified": 0,
        "system_updated": 0,
        "value_updated": null
    },
    {
        "id_variaveis": 1215,
        "linguagem_codigo": "pt-br",
        "modulo": "configuracoes-agendamentos",
        "id": "datas-indisponiveis",
        "valor": "",
        "tipo": "bool",
        "grupo": "host-both",
        "descricao": "Ativar\/Desativar definição de datas indisponíveis para agendamento.",
        "user_modified": 0,
        "system_updated": 0,
        "value_updated": null
    },
    {
        "id_variaveis": 1216,
        "linguagem_codigo": "pt-br",
        "modulo": "configuracoes-agendamentos",
        "id": "calendario-anos",
        "valor": "1",
        "tipo": "number",
        "grupo": "host-both",
        "descricao": "Quantidade máxima de anos que aparece no calendário.",
        "user_modified": 0,
        "system_updated": 0,
        "value_updated": null
    },
    {
        "id_variaveis": 1217,
        "linguagem_codigo": "pt-br",
        "modulo": "configuracoes-agendamentos",
        "id": "calendario-limite-mes-a-frente",
        "valor": "2",
        "tipo": "number",
        "grupo": "host-both",
        "descricao": "Limitar a quantidade de meses a frente do dia atual para mostrar datas disponíveis para agendamento. Por exemplo, se colocar 2 neste campo, significa que apenas o mês atual e o próximo mês aparecerão para agendar no calendário. ",
        "user_modified": 0,
        "system_updated": 0,
        "value_updated": null
    },
    {
        "id_variaveis": 1218,
        "linguagem_codigo": "pt-br",
        "modulo": "configuracoes-agendamentos",
        "id": "fase-escolha-livre",
        "valor": "7",
        "tipo": "number",
        "grupo": "host-both",
        "descricao": "Quantidade em dias antes do dia de um atendimento que o sistema libera a escolha livre deste atendimento para fazer o pré-agendamento.",
        "user_modified": 0,
        "system_updated": 0,
        "value_updated": null
    },
    {
        "id_variaveis": 1219,
        "linguagem_codigo": "pt-br",
        "modulo": "configuracoes-agendamentos",
        "id": "fase-residual",
        "valor": "5",
        "tipo": "number",
        "grupo": "host-both",
        "descricao": "Quantidade em dias antes do dia de um atendimento que o sistema libera a escolha livre deste atendimento para fazer o agendamento das vagas residuais.",
        "user_modified": 0,
        "system_updated": 0,
        "value_updated": null
    },
    {
        "id_variaveis": 1220,
        "linguagem_codigo": "pt-br",
        "modulo": "configuracoes-agendamentos",
        "id": "agendamento-assunto",
        "valor": "Agendamento Efetuado - nº #codigo#",
        "tipo": "string",
        "grupo": "host-admin",
        "descricao": "Assunto dos emails que serão enviados aos agendamentos dos usuários feitos no seu site. ",
        "user_modified": 0,
        "system_updated": 0,
        "value_updated": null
    },
    {
        "id_variaveis": 1221,
        "linguagem_codigo": "pt-br",
        "modulo": "configuracoes-agendamentos",
        "id": "calendario-ferias-ate",
        "valor": "20 January",
        "tipo": "string",
        "grupo": "host-both",
        "descricao": "Data do fim do período de férias com o número do dia seguido do mês em inglês. Por exemplo, fim do período no dia 20 de janeiro deve ser preenchido: 20 January .",
        "user_modified": 0,
        "system_updated": 0,
        "value_updated": null
    },
    {
        "id_variaveis": 1222,
        "linguagem_codigo": "pt-br",
        "modulo": "configuracoes-agendamentos",
        "id": "calendario-ferias-de",
        "valor": "20 December",
        "tipo": "string",
        "grupo": "host-both",
        "descricao": "Data do início do período de férias com o número do dia seguido do mês em inglês. Por exemplo, início do período no dia 20 de dezembro deve ser preenchido: 20 December.",
        "user_modified": 0,
        "system_updated": 0,
        "value_updated": null
    },
    {
        "id_variaveis": 1223,
        "linguagem_codigo": "pt-br",
        "modulo": "configuracoes-agendamentos",
        "id": "desagendamento-assunto",
        "valor": "Cancelamento de Agendamento - nº #codigo#",
        "tipo": "string",
        "grupo": "host-admin",
        "descricao": "Assunto dos emails que serão enviados as exclusões dos agendamentos dos usuários feitos no portal. ",
        "user_modified": 0,
        "system_updated": 0,
        "value_updated": null
    },
    {
        "id_variaveis": 1224,
        "linguagem_codigo": "pt-br",
        "modulo": "configuracoes-agendamentos",
        "id": "dias-semana",
        "valor": "tue,thu",
        "tipo": "string",
        "grupo": "host-both",
        "descricao": "Definir os dias da semana que tem agendamento separados pelo caracter vírgula ',' . Os dias devem ser descritos com 3 cartacteres em inglês. Por exemplo, segunda deve ser escrito 'mon'. Gabarito para todos os dias da semana: sun,mon,tue,wed,thu,fri,sat",
        "user_modified": 0,
        "system_updated": 0,
        "value_updated": null
    },
    {
        "id_variaveis": 1225,
        "linguagem_codigo": "pt-br",
        "modulo": "configuracoes-agendamentos",
        "id": "dias-semana-maximo-vagas",
        "valor": "70",
        "tipo": "string",
        "grupo": "host-both",
        "descricao": "Máximo de vagas de agendamento dos dias da semana. Caso queira definir quantidades diferentes por dia da semana, use ',' separando. Por exemplo, 40,60 .",
        "user_modified": 0,
        "system_updated": 0,
        "value_updated": null
    },
    {
        "id_variaveis": 1226,
        "linguagem_codigo": "pt-br",
        "modulo": "configuracoes-agendamentos",
        "id": "email-confirmacao-assunto",
        "valor": "Confirmação de Agendamento - nº #codigo#",
        "tipo": "string",
        "grupo": "host-admin",
        "descricao": "Assunto dos emails que serão enviados para confirmação de agendamentos dos usuários feitos no seu site.",
        "user_modified": 0,
        "system_updated": 0,
        "value_updated": null
    },
    {
        "id_variaveis": 1227,
        "linguagem_codigo": "pt-br",
        "modulo": "configuracoes-agendamentos",
        "id": "fase-sorteio",
        "valor": "7,5",
        "tipo": "string",
        "grupo": "host-both",
        "descricao": "Período em dias antes do dia de um atendimento que o sistema bloqueia a escolha livre de atendimento para dar tempo para os agendamentos serem confirmados.",
        "user_modified": 0,
        "system_updated": 0,
        "value_updated": null
    },
    {
        "id_variaveis": 1228,
        "linguagem_codigo": "pt-br",
        "modulo": "configuracoes-agendamentos",
        "id": "pre-agendamento-assunto",
        "valor": "Pré-Agendamento Efetuado - nº #codigo#",
        "tipo": "string",
        "grupo": "host-admin",
        "descricao": "Assunto dos emails que serão enviados aos pré-agendamentos dos usuários feitos no seu site. ",
        "user_modified": 0,
        "system_updated": 0,
        "value_updated": null
    },
    {
        "id_variaveis": 1229,
        "linguagem_codigo": "pt-br",
        "modulo": "configuracoes-agendamentos",
        "id": "pre-desagendamento-assunto",
        "valor": "Exclusão Pré-Agendamento - nº #codigo#",
        "tipo": "string",
        "grupo": "host-admin",
        "descricao": "Assunto dos emails que serão enviados as exclusões dos pré-agendamentos dos usuários feitos no seu site.",
        "user_modified": 0,
        "system_updated": 0,
        "value_updated": null
    },
    {
        "id_variaveis": 1230,
        "linguagem_codigo": "pt-br",
        "modulo": "configuracoes-agendamentos",
        "id": "datas-indisponiveis-valores",
        "valor": "",
        "tipo": "datas-multiplas",
        "grupo": "host-both",
        "descricao": "Datas específicas indisponíveis para escolha no agendamento.",
        "user_modified": 0,
        "system_updated": 0,
        "value_updated": null
    },
    {
        "id_variaveis": 1231,
        "linguagem_codigo": "pt-br",
        "modulo": "configuracoes-agendamentos",
        "id": "agendamento-mensagem",
        "valor": "<h2>Seu agendamento foi efetuado com sucesso!<\/h2>\\r\\n<h2>Protocolo n&ordm; #codigo#<\/h2>\\r\\n<p>Voc&ecirc; acabou de fazer um agendamento dentro do sistema de agendamentos do(a) #titulo#:<\/p>\\r\\n<p>Dia:&nbsp;<strong>#data#<\/strong><\/p>\\r\\n<p>Senha:<br \/><strong style=\"font-size: 25px;\">#senha#<\/strong><\/p>\\r\\n<table cellpadding=\"5\">\\r\\n<thead>\\r\\n<tr>\\r\\n<th style=\"margin: 1px; padding: 5px; font-size: 18px; line-height: 20px; min-width: 170px;\"><\/th>\\r\\n<th style=\"margin: 1px; padding: 5px; background-color: #00000008; font-size: 24px; font-weight: bold; line-height: 20px; min-width: 300px;\">Pessoas Agendadas<\/th>\\r\\n<\/tr>\\r\\n<\/thead>\\r\\n<tbody>\\r\\n<tr>\\r\\n<td style=\"margin: 1px; padding: 5px; background-color: #00000008; font-size: 18px; font-weight: bold; line-height: 20px;\">Seu Nome<\/td>\\r\\n<td style=\"margin: 1px; padding: 5px;\">#seu-nome#<\/td>\\r\\n<\/tr>\\r\\n<!-- cel < -->\\r\\n<tr>\\r\\n<td style=\"margin: 1px; padding: 5px; background-color: #00000008; font-size: 18px; font-weight: bold; line-height: 20px;\">Acompanhante #num#<\/td>\\r\\n<td style=\"margin: 1px; padding: 5px;\">#acompanhante#<\/td>\\r\\n<\/tr>\\r\\n<!-- cel > --><\/tbody>\\r\\n<\/table>\\r\\n<p>Caso deseje <strong>CANCELAR<\/strong> o seu agendamento acesse: #url-cancelamento#<\/p>",
        "tipo": "tinymce",
        "grupo": "host-admin",
        "descricao": "Mensagem dos emails que serão enviados aos agendamentos dos usuários feitos no seu site. ",
        "user_modified": 0,
        "system_updated": 0,
        "value_updated": null
    },
    {
        "id_variaveis": 1232,
        "linguagem_codigo": "pt-br",
        "modulo": "configuracoes-agendamentos",
        "id": "desagendamento-mensagem",
        "valor": "<h2>Seu agendamento foi cancelado com sucesso!<\/h2>\\r\\n<h2>Protocolo n&ordm; #codigo#<\/h2>\\r\\n<p>Voc&ecirc; acabou de excluir um agendamento dentro do sistema de agendamentos do(a) #titulo#:<\/p>\\r\\n<p>Dia:&nbsp;<strong>#data#<\/strong><\/p>",
        "tipo": "tinymce",
        "grupo": "host-admin",
        "descricao": "Mensagem dos emails que serão enviados as exclusões dos agendamentos dos usuários feitos no seu site. ",
        "user_modified": 0,
        "system_updated": 0,
        "value_updated": null
    },
    {
        "id_variaveis": 1233,
        "linguagem_codigo": "pt-br",
        "modulo": "configuracoes-agendamentos",
        "id": "email-confirmacao-mensagem",
        "valor": "<h2>Confirme ou cancele o seu agendamento!<\/h2>\\r\\n<h2>Protocolo n&ordm; #codigo#<\/h2>\\r\\n<p>O sistema qualificou o seu pr&eacute;-agendamento para agendamento do(a) #titulo#:<\/p>\\r\\n<p>Dia:&nbsp;<strong>#data#<\/strong><\/p>\\r\\n<div>Para <strong>CONFIRMAR<\/strong> o seu agendamento e receber a sua senha de atendimento acesse: #url-confirmacao# .<\/div>\\r\\n<div>&nbsp;<\/div>\\r\\n<div>Para <strong>CANCELAR<\/strong> o seu agendamento acesse: #url-cancelamento# .<\/div>",
        "tipo": "tinymce",
        "grupo": "host-admin",
        "descricao": "Mensagem dos emails que serão enviados para confirmação de agendamentos dos usuários feitos no seu site. ",
        "user_modified": 0,
        "system_updated": 0,
        "value_updated": null
    },
    {
        "id_variaveis": 1234,
        "linguagem_codigo": "pt-br",
        "modulo": "configuracoes-agendamentos",
        "id": "msg-agendamento-cancelado",
        "valor": "<div class=\"ui green header\">Cancelamento Sucesso<\/div>\\r\\n<p>Agendamento <strong>CANCELADO<\/strong> com sucesso!<\/p>",
        "tipo": "tinymce",
        "grupo": "host-both",
        "descricao": "Mensagem alerta mostrada aos usuários quando o cancelamento de um agendamento foi concluído com sucesso.",
        "user_modified": 0,
        "system_updated": 0,
        "value_updated": null
    },
    {
        "id_variaveis": 1235,
        "linguagem_codigo": "pt-br",
        "modulo": "configuracoes-agendamentos",
        "id": "msg-agendamento-confirmado",
        "valor": "<div class=\"ui green header\">Confirma&ccedil;&atilde;o Sucesso<\/div>\\r\\n<p><span class=\"txt-2\">Agendamento <strong>CONFIRMADO<\/strong> com Sucesso!<\/span><\/p>\\r\\n<table class=\"ui definition table\">\\r\\n<thead>\\r\\n<tr>\\r\\n<th><\/th>\\r\\n<th>Pessoas Agendadas<\/th>\\r\\n<\/tr>\\r\\n<\/thead>\\r\\n<tbody>\\r\\n<tr>\\r\\n<td>Seu Nome<\/td>\\r\\n<td>[[seu-nome]]<\/td>\\r\\n<\/tr>\\r\\n<!-- cel-dados < -->\\r\\n<tr>\\r\\n<td>Acompanhante [[num]]<\/td>\\r\\n<td>[[acompanhante]]<\/td>\\r\\n<\/tr>\\r\\n<!-- cel-dados > --><\/tbody>\\r\\n<\/table>",
        "tipo": "tinymce",
        "grupo": "host-both",
        "descricao": "Mensagem alerta mostrada aos usuários quando a confirmação de um agendamento foi concluído com sucesso.",
        "user_modified": 0,
        "system_updated": 0,
        "value_updated": null
    },
    {
        "id_variaveis": 1236,
        "linguagem_codigo": "pt-br",
        "modulo": "configuracoes-agendamentos",
        "id": "msg-agendamento-data-nao-permitida",
        "valor": "<div class=\"ui red header\">Data N&atilde;o Permitida<\/div>\\r\\n<p>Essa data n&atilde;o &eacute; permitida, escolha outra.<\/p>",
        "tipo": "tinymce",
        "grupo": "host-both",
        "descricao": "Mensagem alerta mostrada aos usuários quando uma data não está disponível.",
        "user_modified": 0,
        "system_updated": 0,
        "value_updated": null
    },
    {
        "id_variaveis": 1237,
        "linguagem_codigo": "pt-br",
        "modulo": "configuracoes-agendamentos",
        "id": "msg-agendamento-expirado",
        "valor": "<div class=\"ui red header\">Per&iacute;odo de Confirma&ccedil;&atilde;o Expirado<\/div>\\r\\n<p>N&atilde;o &eacute; poss&iacute;vel mais confirmar seu agendamento uma vez que o mesmo est&aacute; fora do per&iacute;odo de confirma&ccedil;&atilde;o!<\/p>\\r\\n<p>O per&iacute;odo de confirma&ccedil;&atilde;o compreende o dia <strong>#data_confirmacao_1#<\/strong> at&eacute; o dia <strong>#data_confirmacao_2#<\/strong> .<\/p>",
        "tipo": "tinymce",
        "grupo": "host-both",
        "descricao": "Mensagem alerta mostrada aos usuários quando a confirmação de um agendamento não foi possível pois passou o período de confirmação.",
        "user_modified": 0,
        "system_updated": 0,
        "value_updated": null
    },
    {
        "id_variaveis": 1238,
        "linguagem_codigo": "pt-br",
        "modulo": "configuracoes-agendamentos",
        "id": "msg-agendamento-ja-existe",
        "valor": "<div class=\"ui yellow header\">Agendamento J&aacute; Existe<\/div>\\r\\n<p>Esta data j&aacute; tem agendamento cadastrado em seu nome. N&atilde;o &eacute; permitido agendar duas vezes na mesma data. Caso queira modificar um agendamento, s&oacute; &eacute; poss&iacute;vel removendo o agendamento para a mesma data em <a class=\"_ajax_nao\" href=\"..\/agendamentos\/?tela=agendamentos-anteriores\">Agendamentos<\/a> e criar novamente um novo agendamento para a mesma data, desde que a data esteja liberada para novos agendamentos.<\/p>",
        "tipo": "tinymce",
        "grupo": "host-both",
        "descricao": "Mensagem alerta mostrada aos usuários quando tentarem agendar duas vezes na mesma data. ",
        "user_modified": 0,
        "system_updated": 0,
        "value_updated": null
    },
    {
        "id_variaveis": 1239,
        "linguagem_codigo": "pt-br",
        "modulo": "configuracoes-agendamentos",
        "id": "msg-agendamento-nao-encontrado",
        "valor": "<div class=\"ui red header\">Agendamento N&atilde;o Encontrado<\/div>\\r\\n<p>N&atilde;o foi poss&iacute;vel encontrar o seu agendamento ou o c&oacute;digo de verifica&ccedil;&atilde;o informado est&aacute; expirado.<\/p>\\r\\n<p>&Eacute; poss&iacute;vel que seu agendamento j&aacute; tenha sido confirmado ou cancelado e o c&oacute;digo de verifica&ccedil;&atilde;o de agendamento foi removido do sistema depois de seu uso. Sendo assim, acesse no sistema <a class=\"_ajax_nao\" href=\"agendamentos\">Agendamentos<\/a> e fa&ccedil;a as altera&ccedil;&otilde;es por l&aacute;.<\/p>",
        "tipo": "tinymce",
        "grupo": "host-both",
        "descricao": "Mensagem alerta mostrada aos usuários quando um agendamento não foi encontrado.",
        "user_modified": 0,
        "system_updated": 0,
        "value_updated": null
    },
    {
        "id_variaveis": 1240,
        "linguagem_codigo": "pt-br",
        "modulo": "configuracoes-agendamentos",
        "id": "msg-agendamento-sem-vagas",
        "valor": "<div class=\"ui red header\">Agendamento Sem Vagas<\/div>\\r\\n<p>N&atilde;o &eacute; poss&iacute;vel agendar voc&ecirc; e\/ou seus acompanhantes no dia <strong>#data#<\/strong> pois supera a capacidade de vagas de agendamento no dia em quest&atilde;o!&nbsp;<\/p>\\r\\n<p>Quantidade total de vagas dispon&iacute;veis: <strong>#vagas#<\/strong>.<\/p>\\r\\n<p>Observa&ccedil;&otilde;es:<\/p>\\r\\n<ol>\\r\\n<li>Escolha outro dia e tente novamente.<\/li>\\r\\n<li>Ou ent&atilde;o, diminua a quantidade de acompanhantes e tente novamente.<\/li>\\r\\n<\/ol>",
        "tipo": "tinymce",
        "grupo": "host-both",
        "descricao": "Mensagem alerta mostrada aos usuários quando não tem vagas para um agendamento. ",
        "user_modified": 0,
        "system_updated": 0,
        "value_updated": null
    },
    {
        "id_variaveis": 1241,
        "linguagem_codigo": "pt-br",
        "modulo": "configuracoes-agendamentos",
        "id": "msg-agendamento-suspenso",
        "valor": "<div class=\"ui red header\">Agendamento Suspenso<\/div>\\r\\n<p><span class=\"txt-1\">O sistema de agendamentos est&aacute; suspenso!<\/span><\/p>",
        "tipo": "tinymce",
        "grupo": "host-both",
        "descricao": "Mensagem mostrada aos usuários quando o sistema estiver suspenso.",
        "user_modified": 0,
        "system_updated": 0,
        "value_updated": null
    },
    {
        "id_variaveis": 1242,
        "linguagem_codigo": "pt-br",
        "modulo": "configuracoes-agendamentos",
        "id": "msg-conclusao-agendamento",
        "valor": "<div class=\"ui green header\">Agendamento Conclu&iacute;do com Sucesso!<\/div>\\r\\n<p>Dia:&nbsp;<strong>#data#<\/strong><\/p>\\r\\n<p>Senha:<br \/><strong style=\"font-size: 25px;\">#senha#<\/strong><\/p>\\r\\n<table class=\"ui definition table\">\\r\\n<thead>\\r\\n<tr>\\r\\n<th><\/th>\\r\\n<th>Pessoas Agendadas<\/th>\\r\\n<\/tr>\\r\\n<\/thead>\\r\\n<tbody>\\r\\n<tr>\\r\\n<td>Seu Nome<\/td>\\r\\n<td>#seu-nome#<\/td>\\r\\n<\/tr>\\r\\n<!-- cel < -->\\r\\n<tr>\\r\\n<td>Acompanhante #num#<\/td>\\r\\n<td>#acompanhante#<\/td>\\r\\n<\/tr>\\r\\n<!-- cel > --><\/tbody>\\r\\n<\/table>",
        "tipo": "tinymce",
        "grupo": "host-both",
        "descricao": "Mensagem alerta mostrada aos usuários quando concluir um agendamento. ",
        "user_modified": 0,
        "system_updated": 0,
        "value_updated": null
    },
    {
        "id_variaveis": 1243,
        "linguagem_codigo": "pt-br",
        "modulo": "configuracoes-agendamentos",
        "id": "msg-conclusao-pre-agendamento",
        "valor": "<div class=\"ui green header\">Pr&eacute;-Agendamento Conclu&iacute;do com Sucesso!<\/div>\\r\\n<p>Dia:&nbsp;<strong>#data#<\/strong><\/p>\\r\\n<p><span class=\"ui red text\">IMPORTANTE 1:<\/span> Os pr&eacute;-agendamentos N&Atilde;O S&Atilde;O agendamentos confirmados. Os mesmos passar&atilde;o por uma sorteio pelo sistema dia <span class=\"ui blue text\">#data_sorteio#<\/span> . Caso seu pr&eacute;-agendamento seja sorteado, voc&ecirc; dever&aacute; confirmar o seu agendamento atrav&eacute;s de um email que ser&aacute; enviado no dia <span class=\"ui blue text\">#data_sorteio#<\/span> . Ou ent&atilde;o acessando diretamente nosso sistema ap&oacute;s esta data e escolher a op&ccedil;&atilde;o CONFIRMAR AGENDAMENTO para o dia do seu atendimento. Esta confirma&ccedil;&atilde;o deve ser feita entre <span class=\"ui blue text\">#data_confirmacao_1#<\/span> at&eacute; <span class=\"ui blue text\">#data_confirmacao_2#<\/span> . Caso voc&ecirc; n&atilde;o confirme seu agendamento neste per&iacute;odo, as vagas garantidas no sorteio do seu pr&eacute;-agendamento n&atilde;o ter&atilde;o mais efeito e as vagas ser&atilde;o liberadas para serem escolhidas por outras pessoas via sistema novamente.<\/p>\\r\\n<p><span class=\"ui red text\">IMPORTANTE 2:<\/span> Caso haja mais pr&eacute;-agendamentos do que vagas de atendimento, o sistema ir&aacute; automaticamente fazer um sorteio e enviar&aacute; email de confirma&ccedil;&atilde;o aos sorteados, sen&atilde;o enviar&aacute; email de confirma&ccedil;&atilde;o a todos. Sendo assim, caso voc&ecirc; n&atilde;o receba um email de confirma&ccedil;&atilde;o &eacute; porque n&atilde;o foi sorteado para participar do atendimento.<\/p>\\r\\n<p><span class=\"ui red text\">IMPORTANTE 3:<\/span> Ap&oacute;s o dia <span class=\"ui blue text\">#data_confirmacao_2#<\/span> o sistema de agendamento liberar&aacute; as vagas residuais para serem novamente escolhidas e caso voc&ecirc; n&atilde;o tenha confirmado, ou ent&atilde;o n&atilde;o tenha sido sorteado, poder&aacute; escolher a mesma data para um atendimento. Nesta fase n&atilde;o &eacute; garantido vagas e as mesmas podem ser escolhidas por qualquer um que acessar o sistema.<\/p>",
        "tipo": "tinymce",
        "grupo": "host-both",
        "descricao": "Mensagem alerta mostrada aos usuários quando concluir um pré-agendamento.",
        "user_modified": 0,
        "system_updated": 0,
        "value_updated": null
    },
    {
        "id_variaveis": 1244,
        "linguagem_codigo": "pt-br",
        "modulo": "configuracoes-agendamentos",
        "id": "msg-vagas-residuais-indisponiveis",
        "valor": "<p>N&atilde;o foi poss&iacute;vel confirmar por vagas residuais. Ou porque est&aacute; fora do prazo para confirma&ccedil;&atilde;o ou porque se esgotaram as vagas residuais.<\/p>",
        "tipo": "tinymce",
        "grupo": "host-both",
        "descricao": "Quando não for possível confirmar vagas residuais por estar fora do prazo ou porque ficou sem vagas. ",
        "user_modified": 0,
        "system_updated": 0,
        "value_updated": null
    },
    {
        "id_variaveis": 1245,
        "linguagem_codigo": "pt-br",
        "modulo": "configuracoes-agendamentos",
        "id": "pre-agendamento-mensagem",
        "valor": "<h2>Seu pr&eacute;-agendamento foi efetuado com sucesso!<\/h2>\\r\\n<h2>Protocolo n&ordm; #codigo#<\/h2>\\r\\n<p>Voc&ecirc; acabou de fazer um pr&eacute;-agendamento dentro do sistema de agendamentos do(a) #titulo#:<\/p>\\r\\n<p>Dia:&nbsp;<strong>#data#<\/strong><\/p>\\r\\n<h2>INFORMA&Ccedil;&Otilde;ES IMPORTANTES<\/h2>\\r\\n<div><span class=\"txt-1\"><strong>IMPORTANTE 1<\/strong>:<\/span> Os pr&eacute;-agendamentos N&Atilde;O S&Atilde;O agendamentos confirmados. Os mesmos passar&atilde;o por uma sorteio pelo sistema dia <span class=\"txt-1\">#data_sorteio#<\/span> . Caso seu pr&eacute;-agendamento seja sorteado, voc&ecirc; dever&aacute; confirmar o seu agendamento atrav&eacute;s de um email que ser&aacute; enviado no dia <span class=\"txt-1\">#data_sorteio#<\/span> . Ou ent&atilde;o acessando diretamente nosso sistema ap&oacute;s esta data e escolher a op&ccedil;&atilde;o CONFIRMAR AGENDAMENTO para o dia do seu atendimento. Esta confirma&ccedil;&atilde;o deve ser feita entre <span class=\"txt-1\">#data_confirmacao_1#<\/span> at&eacute; <span class=\"txt-1\">#data_confirmacao_2#<\/span> . Caso voc&ecirc; n&atilde;o confirme seu agendamento neste per&iacute;odo, as vagas garantidas no sorteio do seu pr&eacute;-agendamento n&atilde;o ter&atilde;o mais efeito e as vagas ser&atilde;o liberadas para serem escolhidas por outras pessoas via sistema novamente.<\/div>\\r\\n<div><br \/><span class=\"txt-1\"><strong>IMPORTANTE 2<\/strong>:<\/span> Caso haja mais pr&eacute;-agendamentos do que vagas de atendimento, o sistema ir&aacute; automaticamente fazer um sorteio e enviar&aacute; email de confirma&ccedil;&atilde;o aos sorteados, sen&atilde;o enviar&aacute; email de confirma&ccedil;&atilde;o a todos. Sendo assim, caso voc&ecirc; n&atilde;o receba um email de confirma&ccedil;&atilde;o &eacute; porque n&atilde;o foi sorteado para participar do atendimento.<\/div>\\r\\n<div><br \/><span class=\"txt-1\"><strong>IMPORTANTE 3<\/strong>:<\/span> Ap&oacute;s o dia <span class=\"txt-1\">#data_confirmacao_2#<\/span> o sistema de agendamento liberar&aacute; as vagas residuais para serem novamente escolhidas e caso voc&ecirc; n&atilde;o tenha confirmado, ou ent&atilde;o n&atilde;o tenha sido sorteado, poder&aacute; escolher a mesma data para um atendimento. Nesta fase n&atilde;o &eacute; garantido vagas e as mesmas podem ser escolhidas por qualquer um que acessar o sistema.<\/div>\\r\\n<p>Caso deseje <strong>CANCELAR<\/strong> o seu agendamento acesse: #url-cancelamento#<\/p>",
        "tipo": "tinymce",
        "grupo": "host-admin",
        "descricao": "Mensagem dos emails que serão enviados aos pré-agendamentos dos usuários feitos no seu site. ",
        "user_modified": 0,
        "system_updated": 0,
        "value_updated": null
    },
    {
        "id_variaveis": 1246,
        "linguagem_codigo": "pt-br",
        "modulo": "configuracoes-agendamentos",
        "id": "texto-sem-agendamentos-cadastrados",
        "valor": "<p>Sem agendamentos cadastrados!<\/p>",
        "tipo": "tinymce",
        "grupo": "host-both",
        "descricao": "Texto que aparece na página quando o usuário não tem agendamentos cadastrados.",
        "user_modified": 0,
        "system_updated": 0,
        "value_updated": null
    },
    {
        "id_variaveis": 1247,
        "linguagem_codigo": "pt-br",
        "modulo": "configuracoes-agendamentos",
        "id": "form-msg-data",
        "valor": "É obrigatório escolher uma data antes de enviar.",
        "tipo": "string",
        "grupo": "host-system",
        "descricao": "Mensagem de obrigatoriedade de definição de uma data.",
        "user_modified": 0,
        "system_updated": 0,
        "value_updated": null
    },
    {
        "id_variaveis": 1248,
        "linguagem_codigo": "pt-br",
        "modulo": "configuracoes-agendamentos",
        "id": "form-msg-acompanhante",
        "valor": "É obrigatório preencher todos os nomes dos acompanhantes antes de enviar",
        "tipo": "string",
        "grupo": "host-system",
        "descricao": "Mensagem de obrigatoriedade de preenchimento do nome do acompanhante.",
        "user_modified": 0,
        "system_updated": 0,
        "value_updated": null
    },
    {
        "id_variaveis": 1249,
        "linguagem_codigo": "pt-br",
        "modulo": "configuracoes-agendamentos",
        "id": "max-acompanhantes",
        "valor": "3",
        "tipo": "number",
        "grupo": "host-both",
        "descricao": "Máximo de acompanhantes em uma agendamento",
        "user_modified": 0,
        "system_updated": 0,
        "value_updated": null
    },
    {
        "id_variaveis": 1250,
        "linguagem_codigo": "pt-br",
        "modulo": "configuracoes-agendamentos",
        "id": "titulo-estabelecimento",
        "valor": "Meu Estabelecimento",
        "tipo": "string",
        "grupo": "host-admin",
        "descricao": "Título do seu estabelecimento. Exemplo: minha empresa, minha instituição, etc.",
        "user_modified": 0,
        "system_updated": 0,
        "value_updated": null
    },
    {
        "id_variaveis": 1251,
        "linguagem_codigo": "pt-br",
        "modulo": "configuracoes-agendamentos",
        "id": "status-confirmado",
        "valor": "<span class=\"ui green label\">Confirmado<\/span>",
        "tipo": "string",
        "grupo": "host-system",
        "descricao": "Estado do agendado confirmado",
        "user_modified": 0,
        "system_updated": 0,
        "value_updated": null
    },
    {
        "id_variaveis": 1252,
        "linguagem_codigo": "pt-br",
        "modulo": "configuracoes-agendamentos",
        "id": "status-novo",
        "valor": "<span class=\"ui grey label\">Aguardando Sorteio<\/span>",
        "tipo": "string",
        "grupo": "host-system",
        "descricao": "Estado do agendado novo",
        "user_modified": 0,
        "system_updated": 0,
        "value_updated": null
    },
    {
        "id_variaveis": 1253,
        "linguagem_codigo": "pt-br",
        "modulo": "configuracoes-agendamentos",
        "id": "status-finalizado",
        "valor": "<span class=\"ui grey label\">Finalizado<\/span>",
        "tipo": "string",
        "grupo": "host-system",
        "descricao": "Estado do agendado finalizado",
        "user_modified": 0,
        "system_updated": 0,
        "value_updated": null
    },
    {
        "id_variaveis": 1254,
        "linguagem_codigo": "pt-br",
        "modulo": "configuracoes-agendamentos",
        "id": "status-qualificado",
        "valor": "<span class=\"ui yellow label\">Sorteado - Aguardando Confirmação<\/span>",
        "tipo": "string",
        "grupo": "host-system",
        "descricao": "Estado do agendado qualificado",
        "user_modified": 0,
        "system_updated": 0,
        "value_updated": null
    },
    {
        "id_variaveis": 1255,
        "linguagem_codigo": "pt-br",
        "modulo": "configuracoes-agendamentos",
        "id": "status-nao-qualificado",
        "valor": "<span class=\"ui brown label\">Não Sorteado - Aguardando Vagas Residuais<\/span>",
        "tipo": "string",
        "grupo": "host-system",
        "descricao": "Estado do agendado não qualificado",
        "user_modified": 0,
        "system_updated": 0,
        "value_updated": null
    },
    {
        "id_variaveis": 1256,
        "linguagem_codigo": "pt-br",
        "modulo": "configuracoes-agendamentos",
        "id": "status-vagas-residuais",
        "valor": "<span class=\"ui teal label\">Vagas Residuais Disponíveis<\/span>",
        "tipo": "string",
        "grupo": "host-system",
        "descricao": "Estado do agendado vagas residuais",
        "user_modified": 0,
        "system_updated": 0,
        "value_updated": null
    },
    {
        "id_variaveis": 1257,
        "linguagem_codigo": "pt-br",
        "modulo": "configuracoes-agendamentos",
        "id": "status-sem-vagas-residuais",
        "valor": "<span class=\"ui brown label\">Sem Vagas Residuais<\/span>",
        "tipo": "string",
        "grupo": "host-system",
        "descricao": "Estado do agendado sem vagas residuais",
        "user_modified": 0,
        "system_updated": 0,
        "value_updated": null
    },
    {
        "id_variaveis": 1258,
        "linguagem_codigo": "pt-br",
        "modulo": "configuracoes-agendamentos",
        "id": "teste",
        "valor": "Teste",
        "tipo": "string",
        "grupo": null,
        "descricao": null,
        "user_modified": 0,
        "system_updated": 0,
        "value_updated": null
    },
    {
        "id_variaveis": 1259,
        "linguagem_codigo": "pt-br",
        "modulo": "configuracoes-agendamentos",
        "id": "data-multipla",
        "valor": null,
        "tipo": "datas-multiplas",
        "grupo": null,
        "descricao": "Teste",
        "user_modified": 0,
        "system_updated": 0,
        "value_updated": null
    },
    {
        "id_variaveis": 1260,
        "linguagem_codigo": "pt-br",
        "modulo": "configuracoes-agendamentos",
        "id": "data",
        "valor": "25\/05\/2022 01:00",
        "tipo": "data-hora",
        "grupo": null,
        "descricao": null,
        "user_modified": 0,
        "system_updated": 0,
        "value_updated": null
    },
    {
        "id_variaveis": 1261,
        "linguagem_codigo": "pt-br",
        "modulo": "configuracoes-agendamentos",
        "id": "data-hora",
        "valor": "12\/05\/2012",
        "tipo": "data",
        "grupo": null,
        "descricao": null,
        "user_modified": 0,
        "system_updated": 0,
        "value_updated": null
    },
    {
        "id_variaveis": 1262,
        "linguagem_codigo": "pt-br",
        "modulo": "configuracoes-agendamentos",
        "id": "teste-tinymce",
        "valor": null,
        "tipo": "tinymce",
        "grupo": null,
        "descricao": null,
        "user_modified": 0,
        "system_updated": 0,
        "value_updated": null
    },
    {
        "id_variaveis": 1263,
        "linguagem_codigo": "pt-br",
        "modulo": "configuracoes-agendamentos",
        "id": "texto-agendamentos-cadastrados",
        "valor": "<h2>Pr&eacute;-Agendamentos<\/h2>\\r\\n<p><span class=\"txt-1\">IMPORTANTE 1:<\/span> Os pr&eacute;-agendamentos N&Atilde;O S&Atilde;O agendamentos confirmados. Os mesmos passar&atilde;o por uma sorteio pelo sistema <span class=\"txt-1\">#data_sorteio#<\/span> dias antes do dia do atendimento. Caso seu pr&eacute;-agendamento seja sorteado, voc&ecirc; dever&aacute; confirmar o seu agendamento atrav&eacute;s de um email que ser&aacute; enviado <span class=\"txt-1\">#data_sorteio#<\/span> dias antes do dia do atendimento. Ou ent&atilde;o acessando diretamente nosso sistema ap&oacute;s esta data e escolher a op&ccedil;&atilde;o CONFIRMAR AGENDAMENTO para o dia do seu atendimento. Esta confirma&ccedil;&atilde;o deve ser feita entre <span class=\"txt-1\">#data_confirmacao_1#<\/span> at&eacute; <span class=\"txt-1\">#data_confirmacao_2#<\/span> dias antes do dia do atendimento. Caso voc&ecirc; n&atilde;o confirme seu agendamento neste per&iacute;odo, as vagas garantidas no sorteio do seu pr&eacute;-agendamento n&atilde;o ter&atilde;o mais efeito e as vagas ser&atilde;o liberadas para serem escolhidas por outras pessoas via sistema novamente.<br \/><span class=\"txt-1\">IMPORTANTE 2:<\/span> Caso haja mais pr&eacute;-agendamentos do que vagas de atendimento, o sistema ir&aacute; automaticamente fazer um sorteio e enviar&aacute; email de confirma&ccedil;&atilde;o aos sorteados, sen&atilde;o enviar&aacute; email de confirma&ccedil;&atilde;o a todos. Sendo assim, caso voc&ecirc; n&atilde;o receba um email de confirma&ccedil;&atilde;o &eacute; porque n&atilde;o foi sorteado para participar do atendimento.<br \/><span class=\"txt-1\">IMPORTANTE 3:<\/span> Ap&oacute;s o dia <span class=\"txt-1\">#data_confirmacao_2#<\/span> o sistema de agendamento liberar&aacute; as vagas residuais para serem novamente escolhidas e caso voc&ecirc; n&atilde;o tenha confirmado, ou ent&atilde;o n&atilde;o tenha sido sorteado, poder&aacute; escolher a mesma data para um atendimento. Nesta fase n&atilde;o &eacute; garantido vagas e as mesmas podem ser escolhidas por qualquer um que acessar o sistema.<\/p>\\r\\n<p>#pre_agendamentos#<\/p>\\r\\n<h2>Agendamentos Confirmados<\/h2>\\r\\n<p><span class=\"txt-1\">IMPORTANTE 1:<\/span> &Eacute; obrigat&oacute;rio apresentar no dia do atendimento o nome e a senha fornecida abaixo para voc&ecirc; e seus acompanhantes.<\/p>\\r\\n<p>#agendamentos_confirmados#<\/p>\\r\\n<h2>Agendamentos Antigos<\/h2>\\r\\n<p>#agendamentos-antigos#<\/p>",
        "tipo": "tinymce",
        "grupo": "host-admin",
        "descricao": "Texto que aparece na página quando o usuário têm agendamentos cadastrados.",
        "user_modified": 0,
        "system_updated": 0,
        "value_updated": null
    },
    {
        "id_variaveis": 1264,
        "linguagem_codigo": "pt-br",
        "modulo": "configuracoes-agendamentos",
        "id": "cupom-prioridade-descricao",
        "valor": "Quando fizer um novo agendamento, preencha o código abaixo no campo <b>Cupom de Prioridade<\/b>",
        "tipo": "text",
        "grupo": "host-admin",
        "descricao": "Breve descritivo que aparecerá em todos os cupons de prioridade",
        "user_modified": 0,
        "system_updated": 0,
        "value_updated": null
    },
    {
        "id_variaveis": 1265,
        "linguagem_codigo": "pt-br",
        "modulo": "configuracoes-agendamentos",
        "id": "msg-cupom-prioridade-inativo",
        "valor": "<p>O cupom de prioridade n&uacute;mero <strong>#cupom#<\/strong> est&aacute; inativo no sistema e n&atilde;o &eacute; poss&iacute;vel utiliz&aacute;-lo.<\/p>",
        "tipo": "tinymce",
        "grupo": "host-admin",
        "descricao": "Mensagem de alerta de inatividade de cupom de prioridade",
        "user_modified": 0,
        "system_updated": 0,
        "value_updated": null
    },
    {
        "id_variaveis": 1266,
        "linguagem_codigo": "pt-br",
        "modulo": "configuracoes-agendamentos",
        "id": "msg-cupom-prioridade-vencido",
        "valor": "<p>O cupom de prioridade n&uacute;mero&nbsp;<strong>#cupom#<\/strong>&nbsp;est&aacute; fora do per&iacute;odo de validade! S&oacute; &eacute; poss&iacute;vel utilizar o mesmo entre os dias <strong>#valido_de#<\/strong> at&eacute; <strong>#valido_ate#<\/strong>.<\/p>",
        "tipo": "tinymce",
        "grupo": "host-admin",
        "descricao": "Mensagem de alerta de cupom de prioridade vencido",
        "user_modified": 0,
        "system_updated": 0,
        "value_updated": null
    },
    {
        "id_variaveis": 1267,
        "linguagem_codigo": "pt-br",
        "modulo": "configuracoes-agendamentos",
        "id": "msg-cupom-prioridade-ja-utilizado",
        "valor": "<p>O cupom de prioridade n&uacute;mero&nbsp;<strong>#cupom#<\/strong>&nbsp;J&Aacute; FOI UTILIZADO e n&atilde;o &eacute; poss&iacute;vel utiliz&aacute;-lo novamente.<\/p>",
        "tipo": "tinymce",
        "grupo": "host-admin",
        "descricao": "Mensagem de alerta de cupom de prioridade já utilizado",
        "user_modified": 0,
        "system_updated": 0,
        "value_updated": null
    },
    {
        "id_variaveis": 1268,
        "linguagem_codigo": "pt-br",
        "modulo": "configuracoes-agendamentos",
        "id": "msg-cupom-prioridade-nao-encontrado",
        "valor": "<p>O cupom de prioridade n&uacute;mero&nbsp;<strong>#cupom#<\/strong>&nbsp;n&atilde;o foi encontrado!<\/p>",
        "tipo": "tinymce",
        "grupo": "host-admin",
        "descricao": "Mensagem de alerta de cupom de prioridade não encontrado",
        "user_modified": 0,
        "system_updated": 0,
        "value_updated": null
    },
    {
        "id_variaveis": 1269,
        "linguagem_codigo": "pt-br",
        "modulo": "configuracoes-agendamentos",
        "id": "msg-agendamento-ja-confirmado",
        "valor": "<p>Este agendamento j&aacute; foi confirmado em outra tentativa de confirma&ccedil;&atilde;o e portanto n&atilde;o &eacute; poss&iacute;vel confirmar o mesmo novamente.<\/p>",
        "tipo": "tinymce",
        "grupo": "host-app",
        "descricao": "Mensagem que será mostrada ao usuário quando tentar confirmar novamente um agendamento já confirmado.",
        "user_modified": 0,
        "system_updated": 0,
        "value_updated": null
    },
    {
        "id_variaveis": 1270,
        "linguagem_codigo": "pt-br",
        "modulo": "configuracoes-agendamentos",
        "id": "msg-confirmacao-status-nao-permitido",
        "valor": "<p>N&atilde;o &eacute; poss&iacute;vel confirmar este agendamento uma vez que o mesmo n&atilde;o tem estado permitido pelo sistema para tal.<\/p>",
        "tipo": "tinymce",
        "grupo": "host-app",
        "descricao": "Mensagem que será mostrada ao usuário quando tentar confirmar agendamento com estado não permitido.",
        "user_modified": 0,
        "system_updated": 0,
        "value_updated": null
    },
    {
        "id_variaveis": 1271,
        "linguagem_codigo": "pt-br",
        "modulo": "configuracoes-agendamentos",
        "id": "agendamentos-impressao",
        "valor": "<table class=\"ui unstackable celled very compact table\">\\r\\n    <thead>\\r\\n        <tr>\\r\\n            <th>Nome<\/th>\\r\\n            <th>Senha<\/th>\\r\\n            <!-- th-acompanhantes < --><th>#th-acompanhante#<\/th><!-- th-acompanhantes > -->\\r\\n            <th>Visto<\/th>\\r\\n        <\/tr>\\r\\n    <\/thead>\\r\\n    <tbody>\\r\\n        <!-- cel < --><tr>\\r\\n        <td>#nome#<\/td>\\r\\n        <td>#senha#<\/td>\\r\\n        <!-- td-acompanhantes < --><td>#td-acompanhantes#<\/td><!-- td-acompanhantes > -->\\r\\n        <td> <\/td>\\r\\n        <\/tr><!-- cel > -->\\r\\n    <\/tbody>\\r\\n<\/table>",
        "tipo": "html",
        "grupo": "host-admin",
        "descricao": "Layout html de impressão dos agendamentos confirmados.",
        "user_modified": 0,
        "system_updated": 0,
        "value_updated": null
    },
    {
        "id_variaveis": 1272,
        "linguagem_codigo": "pt-br",
        "modulo": "configuracoes-escalas",
        "id": "escala-ativacao",
        "valor": "1",
        "tipo": "bool",
        "grupo": "host-both",
        "descricao": "Ativar\/Desativar o sistema de escalas",
        "user_modified": 0,
        "system_updated": 0,
        "value_updated": null
    },
    {
        "id_variaveis": 1273,
        "linguagem_codigo": "pt-br",
        "modulo": "configuracoes-escalas",
        "id": "msg-escala-suspenso",
        "valor": "<div class=\"ui red header\">Escalamento Suspenso<\/div>\\r\\n<p><span class=\"txt-1\">O sistema de escalas est&aacute; suspenso!<\/span><\/p>",
        "tipo": "tinymce",
        "grupo": "host-both",
        "descricao": "Mensagem mostrada aos usuários quando o sistema estiver suspenso.",
        "user_modified": 0,
        "system_updated": 0,
        "value_updated": null
    },
    {
        "id_variaveis": 1274,
        "linguagem_codigo": "pt-br",
        "modulo": "configuracoes-escalas",
        "id": "calendario-ferias-de",
        "valor": "20 December",
        "tipo": "string",
        "grupo": "host-both",
        "descricao": "Data do início do período de férias com o número do dia seguido do mês em inglês. Por exemplo, início do período no dia 20 de dezembro deve ser preenchido: 20 December.",
        "user_modified": 0,
        "system_updated": 0,
        "value_updated": null
    },
    {
        "id_variaveis": 1275,
        "linguagem_codigo": "pt-br",
        "modulo": "configuracoes-escalas",
        "id": "calendario-ferias-ate",
        "valor": "20 January",
        "tipo": "string",
        "grupo": "host-both",
        "descricao": "Data do fim do período de férias com o número do dia seguido do mês em inglês. Por exemplo, fim do período no dia 20 de janeiro deve ser preenchido: 20 January .",
        "user_modified": 0,
        "system_updated": 0,
        "value_updated": null
    },
    {
        "id_variaveis": 1276,
        "linguagem_codigo": "pt-br",
        "modulo": "configuracoes-escalas",
        "id": "calendario-anos",
        "valor": "1",
        "tipo": "number",
        "grupo": "host-both",
        "descricao": "Quantidade máxima de anos que aparece no calendário.",
        "user_modified": 0,
        "system_updated": 0,
        "value_updated": null
    },
    {
        "id_variaveis": 1277,
        "linguagem_codigo": "pt-br",
        "modulo": "configuracoes-escalas",
        "id": "dias-semana",
        "valor": "tue,thu",
        "tipo": "string",
        "grupo": "host-both",
        "descricao": "Definir os dias da semana que têm escala separados pelo caracter vírgula ',' . Os dias devem ser descritos com 3 cartacteres em inglês. Por exemplo, segunda deve ser escrito 'mon'. Gabarito para todos os dias da semana: sun,mon,tue,wed,thu,fri,sat",
        "user_modified": 0,
        "system_updated": 0,
        "value_updated": null
    },
    {
        "id_variaveis": 1278,
        "linguagem_codigo": "pt-br",
        "modulo": "configuracoes-escalas",
        "id": "dias-semana-maximo-vagas",
        "valor": "70",
        "tipo": "string",
        "grupo": "host-both",
        "descricao": "Máximo de vagas de escala dos dias da semana. Caso queira definir quantidades diferentes por dia da semana, use ',' separando. Por exemplo, 40,60 para os dias 'tue,thu' nesta ordem.",
        "user_modified": 0,
        "system_updated": 0,
        "value_updated": null
    },
    {
        "id_variaveis": 1279,
        "linguagem_codigo": "pt-br",
        "modulo": "configuracoes-escalas",
        "id": "datas-indisponiveis",
        "valor": null,
        "tipo": "bool",
        "grupo": "host-both",
        "descricao": "Ativar\/Desativar definição de datas indisponíveis para escala.",
        "user_modified": 0,
        "system_updated": 0,
        "value_updated": null
    },
    {
        "id_variaveis": 1280,
        "linguagem_codigo": "pt-br",
        "modulo": "configuracoes-escalas",
        "id": "datas-indisponiveis-valores",
        "valor": null,
        "tipo": "datas-multiplas",
        "grupo": "host-both",
        "descricao": "Datas específicas indisponíveis para escolha na escala.",
        "user_modified": 0,
        "system_updated": 0,
        "value_updated": null
    },
    {
        "id_variaveis": 1281,
        "linguagem_codigo": "pt-br",
        "modulo": "configuracoes-escalas",
        "id": "datas-extras-disponiveis",
        "valor": null,
        "tipo": "bool",
        "grupo": "host-both",
        "descricao": "Ativar\/Desativar definição de datas extras disponíveis para escala.",
        "user_modified": 0,
        "system_updated": 0,
        "value_updated": null
    },
    {
        "id_variaveis": 1282,
        "linguagem_codigo": "pt-br",
        "modulo": "configuracoes-escalas",
        "id": "datas-extras-disponiveis-valores",
        "valor": null,
        "tipo": "datas-multiplas",
        "grupo": "host-both",
        "descricao": "Informar todas as datas que deseja disponibilizar de maneira extra na escala.",
        "user_modified": 0,
        "system_updated": 0,
        "value_updated": null
    },
    {
        "id_variaveis": 1283,
        "linguagem_codigo": "pt-br",
        "modulo": "configuracoes-escalas",
        "id": "datas-extras-dias-semana-maximo-vagas",
        "valor": "70",
        "tipo": "string",
        "grupo": "host-both",
        "descricao": "Máximo de vagas de escala das datas extras dos dias da semana. Caso queira definir quantidades diferentes por dia da semana, use ',' separando. Por exemplo, 40,60 para as datas extras 20\/08\/2022,30\/08\/2022 nesta ordem.",
        "user_modified": 0,
        "system_updated": 0,
        "value_updated": null
    },
    {
        "id_variaveis": 1284,
        "linguagem_codigo": "pt-br",
        "modulo": "configuracoes-escalas",
        "id": "dia-inicio-inscricao",
        "valor": "1",
        "tipo": "number",
        "grupo": "host-both",
        "descricao": "Dia do mês que será feita a liberação da inscrição para um mês na escala.",
        "user_modified": 0,
        "system_updated": 0,
        "value_updated": null
    },
    {
        "id_variaveis": 1285,
        "linguagem_codigo": "pt-br",
        "modulo": "configuracoes-escalas",
        "id": "mes-inicio-inscricao",
        "valor": "1",
        "tipo": "string",
        "grupo": "host-both",
        "descricao": "Quantidade de meses anteriores para a liberação da inscrição para um mês na escala.",
        "user_modified": 0,
        "system_updated": 0,
        "value_updated": null
    },
    {
        "id_variaveis": 1286,
        "linguagem_codigo": "pt-br",
        "modulo": "configuracoes-escalas",
        "id": "dias-inicio-confirmacao",
        "valor": "10",
        "tipo": "string",
        "grupo": "host-both",
        "descricao": "Dias antes do mês da escala que será feito o sorteio e liberação para a confirmação na escala de uma mês.",
        "user_modified": 0,
        "system_updated": 0,
        "value_updated": null
    },
    {
        "id_variaveis": 1287,
        "linguagem_codigo": "pt-br",
        "modulo": "configuracoes-escalas",
        "id": "dias-fim-confirmacao",
        "valor": "3",
        "tipo": "string",
        "grupo": "host-both",
        "descricao": "Dias antes do mês da escala que será finalizado o período de confirmação na escala de uma mês.",
        "user_modified": 0,
        "system_updated": 0,
        "value_updated": null
    },
    {
        "id_variaveis": 1288,
        "linguagem_codigo": "pt-br",
        "modulo": "configuracoes-escalas",
        "id": "periodo-limite-alteracao",
        "valor": "1",
        "tipo": "string",
        "grupo": "host-both",
        "descricao": "Dias antes do dia do evento limite para alteração na escala.",
        "user_modified": 0,
        "system_updated": 0,
        "value_updated": null
    },
    {
        "id_variaveis": 1289,
        "linguagem_codigo": "pt-br",
        "modulo": "configuracoes-escalas",
        "id": "calendario-inicio",
        "valor": "6",
        "tipo": "string",
        "grupo": "host-both",
        "descricao": "Quantidade de meses antes do dia atual para iniciar o calendário.",
        "user_modified": 0,
        "system_updated": 0,
        "value_updated": null
    },
    {
        "id_variaveis": 1290,
        "linguagem_codigo": "pt-br",
        "modulo": "configuracoes-escalas",
        "id": "calendario-fim",
        "valor": "6",
        "tipo": "string",
        "grupo": "host-both",
        "descricao": "Quantidade de meses antes do dia atual para finalizar o calendário.",
        "user_modified": 0,
        "system_updated": 0,
        "value_updated": null
    },
    {
        "id_variaveis": 1291,
        "linguagem_codigo": "pt-br",
        "modulo": "configuracoes-escalas",
        "id": "msg-escalamento-data-nao-permitida",
        "valor": "<p>N&atilde;o foi poss&iacute;vel escalar nas seguintes datas pois as mesmas n&atilde;o s&atilde;o permitidas: <strong>#datas#<\/strong><\/p>",
        "tipo": "tinymce",
        "grupo": "host-both",
        "descricao": "Mensagem de alerta mostrada aos usuários quando alguma data escolhida na escalação não é permitida.",
        "user_modified": 0,
        "system_updated": 0,
        "value_updated": null
    },
    {
        "id_variaveis": 1292,
        "linguagem_codigo": "pt-br",
        "modulo": "configuracoes-escalas",
        "id": "escalamento-assunto",
        "valor": "Escala do mês #mes# criada com sucesso - nº #codigo#",
        "tipo": "string",
        "grupo": "host-admin",
        "descricao": "Assunto dos emails que serão enviados aos escalamentos dos usuários feitos no seu site. ",
        "user_modified": 0,
        "system_updated": 0,
        "value_updated": null
    },
    {
        "id_variaveis": 1293,
        "linguagem_codigo": "pt-br",
        "modulo": "configuracoes-escalas",
        "id": "escalamento-mensagem",
        "valor": "<h2>Sua escala do m&ecirc;s #mes# foi <span style=\"color: blue;\">CRIADA<\/span> com sucesso!<\/h2>\\r\\n<h2>Protocolo n&ordm; #codigo#<\/h2>\\r\\n<p>Voc&ecirc; acabou criar a sua escala dentro do sistema de escalas do(a) #titulo#:<\/p>\\r\\n<p>#calendario#<\/p>\\r\\n<!-- extra < -->\\r\\n<p>#extra#<\/p>\\r\\n<!-- extra > -->\\r\\n<p>Caso deseje <strong>ALTERAR<\/strong> a sua escala do m&ecirc;s, acesse: #url-escalamento#<\/p>",
        "tipo": "tinymce",
        "grupo": "host-admin",
        "descricao": "Mensagem dos emails que serão enviados aos escalamentos dos usuários feitos no seu site.",
        "user_modified": 0,
        "system_updated": 0,
        "value_updated": null
    },
    {
        "id_variaveis": 1294,
        "linguagem_codigo": "pt-br",
        "modulo": "configuracoes-escalas",
        "id": "titulo-estabelecimento",
        "valor": "Meu Estabelecimento",
        "tipo": "string",
        "grupo": "host-admin",
        "descricao": "Título do seu estabelecimento. Exemplo: minha empresa, minha instituição, etc.",
        "user_modified": 0,
        "system_updated": 0,
        "value_updated": null
    },
    {
        "id_variaveis": 1295,
        "linguagem_codigo": "pt-br",
        "modulo": "configuracoes-escalas",
        "id": "msg-conclusao-escalamento",
        "valor": "<p>Escala salva com Sucesso!<\/p>\\r\\n<!-- extra < -->\\r\\n<p>#extra#<\/p>\\r\\n<!-- extra > -->",
        "tipo": "tinymce",
        "grupo": "host-admin",
        "descricao": "Mensagem alerta mostrada aos usuários quando concluir um escalamento. ",
        "user_modified": 0,
        "system_updated": 0,
        "value_updated": null
    },
    {
        "id_variaveis": 1296,
        "linguagem_codigo": "pt-br",
        "modulo": "configuracoes-escalas",
        "id": "msg-extra-conclusao-inscricao",
        "valor": "<p><strong>Importante<\/strong>: essa escala ainda n&atilde;o &eacute; definitiva. Haver&aacute; um processo de qualifica&ccedil;&atilde;o automatizada. Quando ocorrer a qualifica&ccedil;&atilde;o voc&ecirc; ser&aacute; notificado via email e dever&aacute; confirmar as datas entre <strong>#data1#<\/strong> at&eacute; <strong>#data2#<\/strong>. Sen&atilde;o confirmar, as datas escolhidas ser&atilde;o removidas automaticamente da sua escala deste m&ecirc;s.<\/p>",
        "tipo": "tinymce",
        "grupo": "host-admin",
        "descricao": "Mensagem extra que será adicionada na mensagem de conclusão de escala na fase de inscrição.",
        "user_modified": 0,
        "system_updated": 0,
        "value_updated": null
    },
    {
        "id_variaveis": 1297,
        "linguagem_codigo": "pt-br",
        "modulo": "configuracoes-escalas",
        "id": "msg-extra-conclusao-utilizacao",
        "valor": "<p><strong>Importante<\/strong>: essa escala j&aacute; &eacute; definitiva. Ou seja, voc&ecirc; j&aacute; pode utilizar essa escala sem precisar passar por um processo de qualifica&ccedil;&atilde;o.<\/p>",
        "tipo": "tinymce",
        "grupo": "host-admin",
        "descricao": "Mensagem extra que será adicionada na mensagem de conclusão de escala na fase de utilização.",
        "user_modified": 0,
        "system_updated": 0,
        "value_updated": null
    },
    {
        "id_variaveis": 1298,
        "linguagem_codigo": "pt-br",
        "modulo": "configuracoes-escalas",
        "id": "email-confirmacao-assunto",
        "valor": "Escala do mês #mes# qualificada com sucesso - nº #codigo#",
        "tipo": "string",
        "grupo": "host-admin",
        "descricao": "Assunto dos emails que serão enviados após o processo de qualificação dos escalamentos dos usuários feitos no seu site.",
        "user_modified": 0,
        "system_updated": 0,
        "value_updated": null
    },
    {
        "id_variaveis": 1299,
        "linguagem_codigo": "pt-br",
        "modulo": "configuracoes-escalas",
        "id": "email-confirmacao-mensagem",
        "valor": "<h2>Sua escala do m&ecirc;s #mes# foi <span style=\"color: green;\">QUALIFICADA<\/span> com sucesso!<\/h2>\\r\\n<h2>Protocolo n&ordm; #codigo#<\/h2>\\r\\n<p>O processo de qualifica&ccedil;&atilde;o dos escalamentos foram conclu&iacute;dos de maneira automatizada pelo sistema de escalas do(a) #titulo#.<\/p>\\r\\n<p><strong>IMPORTANTE 1<\/strong>: confira todas as datas a seguir. N&atilde;o &eacute; garantia que todas as datas escolhidas foram de fato qualificadas. Segue o calend&aacute;rio completo com todas as datas qualificadas:<\/p>\\r\\n<p>#calendario#<\/p>\\r\\n<!-- extra < -->\\r\\n<p><strong>IMPORTANTE 2<\/strong>: essa escala ainda n&atilde;o &eacute; definitiva. Voc&ecirc; dever&aacute; confirmar as datas entre <strong>#data1#<\/strong> at&eacute; <strong>#data2#<\/strong>. Sen&atilde;o confirmar, as datas escolhidas ser&atilde;o removidas automaticamente da sua escala deste m&ecirc;s.<\/p>\\r\\n<p>Para <strong>CONFIRMAR <\/strong>a sua escala do m&ecirc;s, favor acessar o sistema de escalas e selecionar a op&ccedil;&atilde;o confirmar. Caso contr&aacute;rio, clique na op&ccedil;&atilde;o cancelar. Portanto, acesse o sitema clicando aqui: #url-escalamento#<\/p>",
        "tipo": "tinymce",
        "grupo": "host-admin",
        "descricao": "Mensagem dos emails que serão enviados  após o processo de qualificação dos escalamentos dos usuários feitos no seu site.",
        "user_modified": 0,
        "system_updated": 0,
        "value_updated": null
    },
    {
        "id_variaveis": 1300,
        "linguagem_codigo": "pt-br",
        "modulo": "configuracoes-escalas",
        "id": "msg-datas-sem-vagas",
        "valor": "Não há vagas suficientes na(s) seguinte(s) data(s): #datas#.",
        "tipo": "string",
        "grupo": "host-admin",
        "descricao": "Mensagem que será incluída na mensagem de retorno do salvamento de escala caso não haja vagas em um ou mais datas.",
        "user_modified": 0,
        "system_updated": 0,
        "value_updated": null
    },
    {
        "id_variaveis": 1301,
        "linguagem_codigo": "pt-br",
        "modulo": "configuracoes-escalas",
        "id": "escalamento-confirmar-assunto",
        "valor": "Escala do mês #mes# confirmada com sucesso - nº #codigo#",
        "tipo": "string",
        "grupo": "host-admin",
        "descricao": "Assunto dos emails que serão enviados nas confirmações de escalamentos dos usuários feitos no seu site.",
        "user_modified": 0,
        "system_updated": 0,
        "value_updated": null
    },
    {
        "id_variaveis": 1302,
        "linguagem_codigo": "pt-br",
        "modulo": "configuracoes-escalas",
        "id": "escalamento-confirmar-mensagem",
        "valor": "<h2>Sua escala do m&ecirc;s #mes# foi <span style=\"color: green;\">CONFIRMADA<\/span> com sucesso!<\/h2>\\r\\n<h2>Protocolo n&ordm; #codigo#<\/h2>\\r\\n<p>Voc&ecirc; acabou confirmar a sua escala dentro do sistema de escalas do(a) #titulo#:<\/p>\\r\\n<p>#calendario#<\/p>\\r\\n<p>Caso deseje <strong>ALTERAR<\/strong> a sua escala do m&ecirc;s, acesse: #url-escalamento#<\/p>",
        "tipo": "tinymce",
        "grupo": "host-admin",
        "descricao": "Mensagem dos emails que serão enviados nas confirmações de escalamentos dos usuários feitos no seu site.",
        "user_modified": 0,
        "system_updated": 0,
        "value_updated": null
    },
    {
        "id_variaveis": 1303,
        "linguagem_codigo": "pt-br",
        "modulo": "configuracoes-escalas",
        "id": "msg-conclusao-confirmar-escalamento",
        "valor": "<p>Escala confirmada com Sucesso!<\/p>",
        "tipo": "tinymce",
        "grupo": "host-admin",
        "descricao": "Mensagem alerta mostrada aos usuários quando concluir a confirmação do escalamento.",
        "user_modified": 0,
        "system_updated": 0,
        "value_updated": null
    },
    {
        "id_variaveis": 1304,
        "linguagem_codigo": "pt-br",
        "modulo": "configuracoes-escalas",
        "id": "escalamento-cancelar-assunto",
        "valor": "Escala do mês #mes# cancelada com sucesso - nº #codigo#",
        "tipo": "string",
        "grupo": "host-admin",
        "descricao": "Assunto dos emails que serão enviados nos cancelamentos de escalamentos dos usuários feitos no seu site.",
        "user_modified": 0,
        "system_updated": 0,
        "value_updated": null
    },
    {
        "id_variaveis": 1305,
        "linguagem_codigo": "pt-br",
        "modulo": "configuracoes-escalas",
        "id": "escalamento-cancelar-mensagem",
        "valor": "<h2>Sua escala do m&ecirc;s #mes# foi <span style=\"color: red;\">CANCELADA<\/span> com sucesso!<\/h2>\\r\\n<h2>Protocolo n&ordm; #codigo#<\/h2>\\r\\n<p>Voc&ecirc; acabou cancelar a sua escala dentro do sistema de escalas do(a) #titulo#:<\/p>\\r\\n<p>Caso deseje saber maiores informa&ccedil;&otilde;es da sua escala do m&ecirc;s, acesse: #url-escalamento#<\/p>",
        "tipo": "tinymce",
        "grupo": "host-admin",
        "descricao": "Mensagem dos emails que serão enviados nos cancelamentos de escalamentos dos usuários feitos no seu site.",
        "user_modified": 0,
        "system_updated": 0,
        "value_updated": null
    },
    {
        "id_variaveis": 1306,
        "linguagem_codigo": "pt-br",
        "modulo": "configuracoes-escalas",
        "id": "msg-conclusao-cancelar-escalamento",
        "valor": "<p>Escala cancelada com Sucesso!<\/p>",
        "tipo": "tinymce",
        "grupo": "host-admin",
        "descricao": "Mensagem alerta mostrada aos usuários quando concluir o cancelamento do escalamento.",
        "user_modified": 0,
        "system_updated": 0,
        "value_updated": null
    },
    {
        "id_variaveis": 1307,
        "linguagem_codigo": "pt-br",
        "modulo": "configuracoes-escalas",
        "id": "msg-confirmacao-fora-do-prazo",
        "valor": "<div class=\"ui red header\">Confirma&ccedil;&atilde;o fora do prazo!<\/div>\\r\\n<p><span class=\"txt-1\">N&atilde;o &eacute; poss&iacute;vel confirmar a sua escala devido a mesma estar fora do per&iacute;odo de confirma&ccedil;&atilde;o que vai de <strong>#data1#<\/strong> at&eacute; <strong>#data2#<\/strong>.<br \/><\/span><\/p>",
        "tipo": "tinymce",
        "grupo": "host-admin",
        "descricao": "Mensagem de alerta mostrada aos usuários quando houver uma tentativa de confirmação fora do prazo.",
        "user_modified": 0,
        "system_updated": 0,
        "value_updated": null
    },
    {
        "id_variaveis": 1308,
        "linguagem_codigo": "pt-br",
        "modulo": "configuracoes-escalas",
        "id": "escalas-impressao",
        "valor": "<table class=\"ui unstackable celled very compact table\">\\r\\n    <thead>\\r\\n        <tr>\\r\\n            <th>Nome<\/th>\\r\\n            <th>Visto<\/th>\\r\\n        <\/tr>\\r\\n    <\/thead>\\r\\n    <tbody>\\r\\n        <!-- cel < --><tr>\\r\\n        \t<td>#nome#<\/td>\\r\\n        \t<td> <\/td>\\r\\n        <\/tr><!-- cel > -->\\r\\n    <\/tbody>\\r\\n<\/table>",
        "tipo": "html",
        "grupo": "host-admin",
        "descricao": "Layout html de impressão das escalas.",
        "user_modified": 0,
        "system_updated": 0,
        "value_updated": null
    }
]