{
    "versao": "1.1.0",
    "bibliotecas": [
        "interface",
        "html",
        "html-editor"
    ],
    "id_numerico": "id_forms_search",
    "tabela": {
        "nome": "forms_search",
        "nome_especifico": "name",
        "id": "id",
        "id_numerico": "id_forms_search",
        "status": "status",
        "versao": "version",
        "data_criacao": "created_at",
        "data_modificacao": "updated_at",
        "config": {
            "strategy": "natural_key",
            "natural_key_columns": [
                "language",
                "module",
                "id"
            ],
            "preserve_on_user_modified": [
                "name",
                "fields_schema"
            ],
            "insert_only": false
        },
        "deletar": []
    },
    "resources": {
        "pt-br": {
            "widgets": [
                {
                    "id": "forms-search",
                    "name": "Formulário de Busca",
                    "icon": "search",
                    "tabela": "forms_search"
                }
            ],
            "ai_prompts_targets": [
                {
                    "id": "forms-search",
                    "name": "Formulário de Busca"
                }
            ],
            "ai_modes": [
                {
                    "id": "forms-search",
                    "name": "Formulário de Busca",
                    "target": "forms-search",
                    "default": true,
                    "version": "1.0",
                    "checksum": {
                        "md": ""
                    }
                }
            ],
            "form_info": {
                "name": "Nome do Formulário",
                "id": "id-do-formulario",
                "description": "Descrição do formulário.",
                "fields_schema": {
                    "form_action": "pages-index-search\/",
                    "fields": [
                        {
                            "type": "select",
                            "name": "categoria",
                            "label": "Categoria",
                            "options": [
                                "noticias:Notícias",
                                "servicos:Serviços"
                            ],
                            "required": false
                        }
                    ]
                }
            },
            "layouts": [
                {
                    "name": "Página Simples TailwindCSS",
                    "id": "pagina-simples-tailwindcss",
                    "framework_css": "tailwindcss",
                    "version": "1.4",
                    "checksum": {
                        "html": "5d5efc9849f45c5a257ee4e6fff49d16",
                        "css": "",
                        "combined": "5d5efc9849f45c5a257ee4e6fff49d16"
                    }
                }
            ],
            "components": [
                {
                    "name": "Formulário Definições Informações",
                    "id": "forms-search-info-definition",
                    "version": "1.3",
                    "checksum": {
                        "html": "ce0a2a07932f9a16f591f1593bc3e39f",
                        "css": "",
                        "combined": "ce0a2a07932f9a16f591f1593bc3e39f"
                    }
                }
            ],
            "templates": [
                {
                    "name": "Barra de Busca Clássica",
                    "id": "forms-search-contato-basico",
                    "target": "forms-search",
                    "framework_css": "tailwindcss",
                    "version": "1.3",
                    "checksum": {
                        "html": "fd7d92ea845875df031ba6dc93115d04",
                        "css": "",
                        "combined": "fd7d92ea845875df031ba6dc93115d04"
                    }
                },
                {
                    "name": "Busca Minimalista",
                    "id": "forms-search-newsletter-newsletter",
                    "target": "forms-search",
                    "framework_css": "tailwindcss",
                    "version": "1.3",
                    "checksum": {
                        "html": "c0f20a726b9f622e665666c681ade211",
                        "css": "",
                        "combined": "c0f20a726b9f622e665666c681ade211"
                    }
                },
                {
                    "name": "Busca Hero",
                    "id": "forms-search-registro-usuario",
                    "target": "forms-search",
                    "framework_css": "tailwindcss",
                    "version": "1.3",
                    "checksum": {
                        "html": "96a89aef50b84b5174be5ed4916a20a3",
                        "css": "",
                        "combined": "96a89aef50b84b5174be5ed4916a20a3"
                    }
                },
                {
                    "name": "Busca Compacta",
                    "id": "forms-search-pesquisa-satisfacao",
                    "target": "forms-search",
                    "framework_css": "tailwindcss",
                    "version": "1.3",
                    "checksum": {
                        "html": "bf90c989f23a029605e04542f5ab4edc",
                        "css": "",
                        "combined": "bf90c989f23a029605e04542f5ab4edc"
                    }
                },
                {
                    "name": "Busca em Alto Contraste",
                    "id": "forms-search-suporte-tecnico",
                    "target": "forms-search",
                    "framework_css": "tailwindcss",
                    "version": "1.3",
                    "checksum": {
                        "html": "d1ba74fc2f69643b89f2855f371c848c",
                        "css": "",
                        "combined": "d1ba74fc2f69643b89f2855f371c848c"
                    }
                }
            ],
            "pages": [
                {
                    "name": "Formulários Listar",
                    "id": "forms-search-list",
                    "layout": "layout-administrativo-do-gestor",
                    "path": "forms-search\/",
                    "type": "system",
                    "option": "listar",
                    "root": true,
                    "version": "1.0",
                    "checksum": {
                        "html": "",
                        "css": "",
                        "combined": ""
                    }
                },
                {
                    "name": "Formulários Visualizar",
                    "id": "forms-search-view",
                    "layout": "layout-administrativo-do-gestor",
                    "path": "forms-search\/view\/",
                    "type": "system",
                    "option": "visualizar",
                    "version": "1.11",
                    "checksum": {
                        "html": "9d78df67183fc363bf48cd602e4e09e4",
                        "css": "",
                        "combined": "9d78df67183fc363bf48cd602e4e09e4"
                    }
                },
                {
                    "name": "Formulários Adicionar",
                    "id": "forms-search-adicionar",
                    "layout": "layout-administrativo-do-gestor",
                    "path": "forms-search\/adicionar\/",
                    "type": "system",
                    "option": "adicionar",
                    "version": "1.13",
                    "checksum": {
                        "html": "e42652b4e9398045a8ab7f40eb7a155d",
                        "css": "aa43d6aa4dec695c666f726474800b97",
                        "combined": "1dd1ced91d2edfdc3ca098ca7e88d9b4"
                    }
                },
                {
                    "name": "Formulários Editar",
                    "id": "forms-search-editar",
                    "layout": "layout-administrativo-do-gestor",
                    "path": "forms-search\/editar\/",
                    "type": "system",
                    "option": "editar",
                    "version": "1.11",
                    "checksum": {
                        "html": "a95b652093285adea976724b681d4a1b",
                        "css": "aa43d6aa4dec695c666f726474800b97",
                        "combined": "290d0a2b92e9ccaa5253d7563c0a3606"
                    }
                },
                {
                    "name": "Formulários Clonar",
                    "id": "forms-search-clonar",
                    "layout": "layout-administrativo-do-gestor",
                    "path": "forms-search\/clonar\/",
                    "type": "system",
                    "option": "clonar",
                    "version": "1.10",
                    "checksum": {
                        "html": "37e303da6842c030af58c2dccc27088d",
                        "css": "aa43d6aa4dec695c666f726474800b97",
                        "combined": "b58e6a59c5ec56958e587e46dbb9ac10"
                    }
                }
            ],
            "variables": [
                {
                    "id": "form-name-label",
                    "value": "Nome",
                    "type": "string"
                },
                {
                    "id": "form-module-placeholder",
                    "value": "Selecione opcionalmente um módulo",
                    "type": "string"
                },
                {
                    "id": "form-module-label",
                    "value": "Módulo",
                    "type": "string"
                },
                {
                    "id": "form-template_id-label",
                    "value": "Template (Recurso)",
                    "type": "string"
                },
                {
                    "id": "form-fields_schema-label",
                    "value": "Esquema dos Campos",
                    "type": "string"
                },
                {
                    "id": "form-description-label",
                    "value": "Descrição",
                    "type": "string"
                }
            ]
        },
        "en": {
            "widgets": [
                {
                    "id": "forms-search",
                    "name": "Search Form",
                    "icon": "search",
                    "tabela": "forms_search"
                }
            ],
            "ai_prompts_targets": [
                {
                    "id": "forms-search",
                    "name": "Search Form"
                }
            ],
            "ai_modes": [
                {
                    "id": "forms-search",
                    "name": "Search Form",
                    "target": "forms-search",
                    "default": true,
                    "version": "1.0",
                    "checksum": {
                        "md": ""
                    }
                }
            ],
            "form_info": {
                "name": "Form Name",
                "id": "form-id",
                "description": "Form description.",
                "fields_schema": {
                    "form_action": "pages-index-search\/",
                    "fields": [
                        {
                            "type": "select",
                            "name": "category",
                            "label": "Category",
                            "options": [
                                "news:News",
                                "services:Services"
                            ],
                            "required": false
                        }
                    ]
                }
            },
            "layouts": [
                {
                    "name": "Simple Page TailwindCSS",
                    "id": "pagina-simples-tailwindcss",
                    "framework_css": "tailwindcss",
                    "version": "1.4",
                    "checksum": {
                        "html": "",
                        "css": "",
                        "combined": ""
                    }
                }
            ],
            "components": [
                {
                    "name": "Forms Info Definition",
                    "id": "forms-search-info-definition",
                    "version": "1.3",
                    "checksum": {
                        "html": "dd63ec346f22f129cdf4bfaab91d64f4",
                        "css": "",
                        "combined": "dd63ec346f22f129cdf4bfaab91d64f4"
                    }
                }
            ],
            "templates": [
                {
                    "name": "Classic Search Bar",
                    "id": "forms-search-contato-basico",
                    "target": "forms-search",
                    "framework_css": "tailwindcss",
                    "version": "1.3",
                    "checksum": {
                        "html": "cf3903ac104e9cbce373fe93870f52b2",
                        "css": "",
                        "combined": "cf3903ac104e9cbce373fe93870f52b2"
                    }
                },
                {
                    "name": "Minimal Search",
                    "id": "forms-search-newsletter-newsletter",
                    "target": "forms-search",
                    "framework_css": "tailwindcss",
                    "version": "1.3",
                    "checksum": {
                        "html": "36447f25d7cd4b37aba2d719dca15751",
                        "css": "",
                        "combined": "36447f25d7cd4b37aba2d719dca15751"
                    }
                },
                {
                    "name": "Hero Search",
                    "id": "forms-search-registro-usuario",
                    "target": "forms-search",
                    "framework_css": "tailwindcss",
                    "version": "1.3",
                    "checksum": {
                        "html": "461692ddf2544ac9459e0780a34f8c5e",
                        "css": "",
                        "combined": "461692ddf2544ac9459e0780a34f8c5e"
                    }
                },
                {
                    "name": "Compact Search",
                    "id": "forms-search-pesquisa-satisfacao",
                    "target": "forms-search",
                    "framework_css": "tailwindcss",
                    "version": "1.3",
                    "checksum": {
                        "html": "1027c76542221c3c42a2140ea2d6b623",
                        "css": "",
                        "combined": "1027c76542221c3c42a2140ea2d6b623"
                    }
                },
                {
                    "name": "High Contrast Search",
                    "id": "forms-search-suporte-tecnico",
                    "target": "forms-search",
                    "framework_css": "tailwindcss",
                    "version": "1.3",
                    "checksum": {
                        "html": "11d320cebf6fda866728b427dbe432e4",
                        "css": "",
                        "combined": "11d320cebf6fda866728b427dbe432e4"
                    }
                }
            ],
            "pages": [
                {
                    "name": "Forms List",
                    "id": "forms-search-list",
                    "layout": "layout-administrativo-do-gestor",
                    "path": "forms-search\/",
                    "type": "system",
                    "option": "listar",
                    "root": true,
                    "version": "1.0",
                    "checksum": {
                        "html": "",
                        "css": "",
                        "combined": ""
                    }
                },
                {
                    "name": "Forms View",
                    "id": "forms-search-view",
                    "layout": "layout-administrativo-do-gestor",
                    "path": "forms-search\/view\/",
                    "type": "system",
                    "option": "visualizar",
                    "version": "1.14",
                    "checksum": {
                        "html": "08418961498fe8037d93d3cd32be5351",
                        "css": "",
                        "combined": "08418961498fe8037d93d3cd32be5351"
                    }
                },
                {
                    "name": "Forms Add",
                    "id": "forms-search-adicionar",
                    "layout": "layout-administrativo-do-gestor",
                    "path": "forms-search\/adicionar\/",
                    "type": "system",
                    "option": "adicionar",
                    "version": "1.15",
                    "checksum": {
                        "html": "5a4c4cfba6bcdb3c1792ba6fb9172620",
                        "css": "aa43d6aa4dec695c666f726474800b97",
                        "combined": "26b40b1f988e54758973c74d1d7c40e7"
                    }
                },
                {
                    "name": "Forms Edit",
                    "id": "forms-search-editar",
                    "layout": "layout-administrativo-do-gestor",
                    "path": "forms-search\/editar\/",
                    "type": "system",
                    "option": "editar",
                    "version": "1.13",
                    "checksum": {
                        "html": "6bc5955150ef9ffb07143d3ee7beef62",
                        "css": "aa43d6aa4dec695c666f726474800b97",
                        "combined": "c11d2a3fdf51dda67d8693a3d59b8d51"
                    }
                },
                {
                    "name": "Forms Clone",
                    "id": "forms-search-clonar",
                    "layout": "layout-administrativo-do-gestor",
                    "path": "forms-search\/clonar\/",
                    "type": "system",
                    "option": "clonar",
                    "version": "1.12",
                    "checksum": {
                        "html": "e8b5686d8ff9ab178dfca6f9e39081fe",
                        "css": "aa43d6aa4dec695c666f726474800b97",
                        "combined": "52f66111590e158ef9ddf254831acae2"
                    }
                }
            ],
            "variables": [
                {
                    "id": "form-name-label",
                    "value": "Name",
                    "type": "string"
                },
                {
                    "id": "form-module-placeholder",
                    "value": "Optionally select a module",
                    "type": "string"
                },
                {
                    "id": "form-module-label",
                    "value": "Module",
                    "type": "string"
                },
                {
                    "id": "form-template_id-label",
                    "value": "Template (Resource)",
                    "type": "string"
                },
                {
                    "id": "form-fields_schema-label",
                    "value": "Fields Schema",
                    "type": "string"
                },
                {
                    "id": "form-description-label",
                    "value": "Description",
                    "type": "string"
                }
            ]
        }
    }
}
